Workbook

Sheet Instruções
B1: Base de Preços PROBUILT – preços reais
B2: v1.0 · Margem calculada SOBRE O CUSTO · Estrutura compatível com a folha _Produção_Folha_de_orçamento.xlsx
B4: COMO FUNCIONA O PREÇO
B5: 1. Custo direto | C5: Soma de Mão de obra + Materiais + Equipamento + Subempreitada (colunas E–H). Se o artigo ainda não estiver decomposto, usa o «Preço global» (coluna I).
B6: 2. Custo c/ encargos | C6: Cada parcela é agravada pela percentagem de encargos da folha Config (iguais à sua folha de orçamento: MO 1 %, Mat. 3 %, Equip. 2 %, Subemp. 2 %). O preço global usa o encargo médio.
B7: 3. Preço de venda | C7: PV = Custo c/ encargos × (1 + Margem). A margem é SOBRE O CUSTO. Por omissão usa a margem padrão da Config; pode definir uma margem própria por artigo (coluna L).
B8: Exemplo | C8: Custo c/ encargos 100,00 € e margem 20 % → PV = 120,00 €. (A base 2026 anterior fazia 100 / 0,75 = 133,33 €, ou seja, 33 % sobre o custo.)
B10: FIABILIDADE DO PREÇO (coluna R)
B11: A | C11: Preço real: fatura, contrato ou adjudicação.
B12: B | C12: Preço de orçamento próprio ou proposta de subempreiteiro/fornecedor.
B13: C | C13: Referência de mercado – usar com cautela e substituir logo que haja preço B ou A.
B15: CÉLULAS A PREENCHER / CORES
B16: Fundo amarelo | C16: Dados de entrada (decomposição, preço global, margem própria, fonte, obra, data, fiabilidade).
B17: Texto azul | C17: Valor introduzido manualmente (preço).
B18: Texto preto | C18: Fórmula – não editar.
B20: REGISTO DE PREÇOS (folha Registo)
B21: Para que serve | C21: Sempre que receber um preço novo (proposta, fatura, orçamento), registe-o com o código do artigo. A Base mostra automaticamente o n.º de registos e o último preço registado, para decidir quando atualizar o preço do artigo.
B22: Exemplo | C22: 15/10/2026 · ARQ.21 · Moradia X · Proposta pintor Y · 7,90 € · B
B24: NOTAS
C25: • Origem: 115 artigos da BASE_PRECOS_2026 (referência de mercado, fiabilidade C) + 32 artigos do orçamento da Ribeira (L99), preços de custo antes de margem (fiabilidade B).
C26: • Os preços da Ribeira incluem agravamento por acesso condicionado – ver observações; numa obra sem condicionantes podem ser mais baixos.
C27: • HID.05–HID.08 passaram para ESG e TER.04–TER.05 para ACU (códigos mantidos para rastreabilidade).
C28: • Especialidades alinhadas com as pastas do Drive: ARQ, EST, HID (inclui PLU), ESG, ELE, ITED, AVAC, GAS, SCIE, TERM, ACU, + GER e CARP para orçamento.

Sheet Base
A1: BASE DE PREÇOS PROBUILT
A2: ="Margem padrão sobre o custo: "&TEXT(Config!$C$3,"0%")&" · Artigos: "&COUNTA(A5:A1000)&" · Fiabilidade A/B/C: "&COUNTIF(R5:R1000,"A")&" / "&COUNTIF(R5:R1000,"B")&" / "&COUNTIF(R5:R1000,"C") -> Margem padrão sobre o custo: 20% · Artigos: 147 · Fiabilidade A/B/C: 0 / 32 / 115
A4: Cód. | B4: Designação | C4: Esp. | D4: Un. | E4: Mão de obra (€) | F4: Materiais (€) | G4: Equipamento (€) | H4: Subempreitada (€) | I4: Preço global s/ decomp. (€) | J4: Custo direto (€) | K4: Custo c/ encargos (€) | L4: Margem própria (s/ custo) | M4: Margem aplicada | N4: PV unitário (€) | O4: Fonte | P4: Obra de origem | Q4: Data | R4: Fiabilidade | S4: N.º registos | T4: Último preço registado (€) | U4: Observações
A5: GER.01 | B5: Estaleiro: proteções de pavimentos e superfícies, sinalização, condicionamento de acessos (obra pequena) | C5: GER | D5: vg | I5: 350 | J5: =IF(AND(A5="",B5=""),"",IF(SUM(E5:H5)>0,SUM(E5:H5),I5)) -> 350 | K5: =IF(J5="","",ROUND(IF(SUM(E5:H5)>0,E5*(1+Config!$C$4)+F5*(1+Config!$C$5)+G5*(1+Config!$C$6)+H5*(1+Config!$C$7),I5*(1+Config!$C$8)),2)) -> 357 | M5: =IF(J5="","",IF(L5="",Config!$C$3,L5)) -> 0.2 | N5: =IF(K5="","",ROUND(K5*(1+M5),2)) -> 428.4 | O5: Orçamento próprio (custo, antes de margem) | P5: Ribeira – remodelação (L99) | Q5: 2026 | R5: B | S5: =IF(A5="","",COUNTIF(Registo!$B$2:$B$501,A5)) -> 0 | T5: =IF(OR(A5="",S5=0),"",LOOKUP(2,1/(Registo!$B$2:$B$501=A5),Registo!$E$2:$E$501)) | U5: Inclui agravamento por acesso condicionado (transporte manual 100 m + escadaria, 1.º andar s/ elevador)
A6: GER.02 | B6: Limpeza final de obra e entrega em condições de habitabilidade (obra pequena) | C6: GER | D6: vg | I6: 500 | J6: =IF(AND(A6="",B6=""),"",IF(SUM(E6:H6)>0,SUM(E6:H6),I6)) -> 500 | K6: =IF(J6="","",ROUND(IF(SUM(E6:H6)>0,E6*(1+Config!$C$4)+F6*(1+Config!$C$5)+G6*(1+Config!$C$6)+H6*(1+Config!$C$7),I6*(1+Config!$C$8)),2)) -> 510 | M6: =IF(J6="","",IF(L6="",Config!$C$3,L6)) -> 0.2 | N6: =IF(K6="","",ROUND(K6*(1+M6),2)) -> 612 | O6: Orçamento próprio (custo, antes de margem) | P6: Ribeira – remodelação (L99) | Q6: 2026 | R6: B | S6: =IF(A6="","",COUNTIF(Registo!$B$2:$B$501,A6)) -> 0 | T6: =IF(OR(A6="",S6=0),"",LOOKUP(2,1/(Registo!$B$2:$B$501=A6),Registo!$E$2:$E$501)) | U6: Inclui agravamento por acesso condicionado (transporte manual 100 m + escadaria, 1.º andar s/ elevador)
A7: ARQ.01 | B7: Demolição de paredes em tijolo | C7: ARQ | D7: m² | I7: 12 | J7: =IF(AND(A7="",B7=""),"",IF(SUM(E7:H7)>0,SUM(E7:H7),I7)) -> 12 | K7: =IF(J7="","",ROUND(IF(SUM(E7:H7)>0,E7*(1+Config!$C$4)+F7*(1+Config!$C$5)+G7*(1+Config!$C$6)+H7*(1+Config!$C$7),I7*(1+Config!$C$8)),2)) -> 12.24 | M7: =IF(J7="","",IF(L7="",Config!$C$3,L7)) -> 0.2 | N7: =IF(K7="","",ROUND(K7*(1+M7),2)) -> 14.69 | O7: Referência de mercado Porto/Aveiro (BASE_PRECOS_2026) | Q7: Jun-2026 | R7: C | S7: =IF(A7="","",COUNTIF(Registo!$B$2:$B$501,A7)) -> 0 | T7: =IF(OR(A7="",S7=0),"",LOOKUP(2,1/(Registo!$B$2:$B$501=A7),Registo!$E$2:$E$501))
A8: ARQ.02 | B8: Demolição de pavimento em betão | C8: ARQ | D8: m² | I8: 18 | J8: =IF(AND(A8="",B8=""),"",IF(SUM(E8:H8)>0,SUM(E8:H8),I8)) -> 18 | K8: =IF(J8="","",ROUND(IF(SUM(E8:H8)>0,E8*(1+Config!$C$4)+F8*(1+Config!$C$5)+G8*(1+Config!$C$6)+H8*(1+Config!$C$7),I8*(1+Config!$C$8)),2)) -> 18.36 | M8: =IF(J8="","",IF(L8="",Config!$C$3,L8)) -> 0.2 | N8: =IF(K8="","",ROUND(K8*(1+M8),2)) -> 22.03 | O8: Referência de mercado Porto/Aveiro (BASE_PRECOS_2026) | Q8: Jun-2026 | R8: C | S8: =IF(A8="","",COUNTIF(Registo!$B$2:$B$501,A8)) -> 0 | T8: =IF(OR(A8="",S8=0),"",LOOKUP(2,1/(Registo!$B$2:$B$501=A8),Registo!$E$2:$E$501))
A9: ARQ.03 | B9: Demolição de cobertura em telha | C9: ARQ | D9: m² | I9: 14 | J9: =IF(AND(A9="",B9=""),"",IF(SUM(E9:H9)>0,SUM(E9:H9),I9)) -> 14 | K9: =IF(J9="","",ROUND(IF(SUM(E9:H9)>0,E9*(1+Config!$C$4)+F9*(1+Config!$C$5)+G9*(1+Config!$C$6)+H9*(1+Config!$C$7),I9*(1+Config!$C$8)),2)) -> 14.28 | M9: =IF(J9="","",IF(L9="",Config!$C$3,L9)) -> 0.2 | N9: =IF(K9="","",ROUND(K9*(1+M9),2)) -> 17.14 | O9: Referência de mercado Porto/Aveiro (BASE_PRECOS_2026) | Q9: Jun-2026 | R9: C | S9: =IF(A9="","",COUNTIF(Registo!$B$2:$B$501,A9)) -> 0 | T9: =IF(OR(A9="",S9=0),"",LOOKUP(2,1/(Registo!$B$2:$B$501=A9),Registo!$E$2:$E$501))
A10: ARQ.04 | B10: Paredes exteriores pano duplo tijolo 11+11 c/ caixa ar | C10: ARQ | D10: m² | I10: 55 | J10: =IF(AND(A10="",B10=""),"",IF(SUM(E10:H10)>0,SUM(E10:H10),I10)) -> 55 | K10: =IF(J10="","",ROUND(IF(SUM(E10:H10)>0,E10*(1+Config!$C$4)+F10*(1+Config!$C$5)+G10*(1+Config!$C$6)+H10*(1+Config!$C$7),I10*(1+Config!$C$8)),2)) -> 56.1 | M10: =IF(J10="","",IF(L10="",Config!$C$3,L10)) -> 0.2 | N10: =IF(K10="","",ROUND(K10*(1+M10),2)) -> 67.32 | O10: Referência de mercado Porto/Aveiro (BASE_PRECOS_2026) | Q10: Jun-2026 | R10: C | S10: =IF(A10="","",COUNTIF(Registo!$B$2:$B$501,A10)) -> 0 | T10: =IF(OR(A10="",S10=0),"",LOOKUP(2,1/(Registo!$B$2:$B$501=A10),Registo!$E$2:$E$501))
A11: ARQ.05 | B11: Paredes interiores tijolo 11 | C11: ARQ | D11: m² | I11: 32 | J11: =IF(AND(A11="",B11=""),"",IF(SUM(E11:H11)>0,SUM(E11:H11),I11)) -> 32 | K11: =IF(J11="","",ROUND(IF(SUM(E11:H11)>0,E11*(1+Config!$C$4)+F11*(1+Config!$C$5)+G11*(1+Config!$C$6)+H11*(1+Config!$C$7),I11*(1+Config!$C$8)),2)) -> 32.64 | M11: =IF(J11="","",IF(L11="",Config!$C$3,L11)) -> 0.2 | N11: =IF(K11="","",ROUND(K11*(1+M11),2)) -> 39.17 | O11: Referência de mercado Porto/Aveiro (BASE_PRECOS_2026) | Q11: Jun-2026 | R11: C | S11: =IF(A11="","",COUNTIF(Registo!$B$2:$B$501,A11)) -> 0 | T11: =IF(OR(A11="",S11=0),"",LOOKUP(2,1/(Registo!$B$2:$B$501=A11),Registo!$E$2:$E$501))
A12: ARQ.06 | B12: Paredes interiores tijolo 7 | C12: ARQ | D12: m² | I12: 26 | J12: =IF(AND(A12="",B12=""),"",IF(SUM(E12:H12)>0,SUM(E12:H12),I12)) -> 26 | K12: =IF(J12="","",ROUND(IF(SUM(E12:H12)>0,E12*(1+Config!$C$4)+F12*(1+Config!$C$5)+G12*(1+Config!$C$6)+H12*(1+Config!$C$7),I12*(1+Config!$C$8)),2)) -> 26.52 | M12: =IF(J12="","",IF(L12="",Config!$C$3,L12)) -> 0.2 | N12: =IF(K12="","",ROUND(K12*(1+M12),2)) -> 31.82 | O12: Referência de mercado Porto/Aveiro (BASE_PRECOS_2026) | Q12: Jun-2026 | R12: C | S12: =IF(A12="","",COUNTIF(Registo!$B$2:$B$501,A12)) -> 0 | T12: =IF(OR(A12="",S12=0),"",LOOKUP(2,1/(Registo!$B$2:$B$501=A12),Registo!$E$2:$E$501))
A13: ARQ.07 | B13: Reboco interior argamassa tradicional | C13: ARQ | D13: m² | I13: 18 | J13: =IF(AND(A13="",B13=""),"",IF(SUM(E13:H13)>0,SUM(E13:H13),I13)) -> 18 | K13: =IF(J13="","",ROUND(IF(SUM(E13:H13)>0,E13*(1+Config!$C$4)+F13*(1+Config!$C$5)+G13*(1+Config!$C$6)+H13*(1+Config!$C$7),I13*(1+Config!$C$8)),2)) -> 18.36 | M13: =IF(J13="","",IF(L13="",Config!$C$3,L13)) -> 0.2 | N13: =IF(K13="","",ROUND(K13*(1+M13),2)) -> 22.03 | O13: Referência de mercado Porto/Aveiro (BASE_PRECOS_2026) | Q13: Jun-2026 | R13: C | S13: =IF(A13="","",COUNTIF(Registo!$B$2:$B$501,A13)) -> 0 | T13: =IF(OR(A13="",S13=0),"",LOOKUP(2,1/(Registo!$B$2:$B$501=A13),Registo!$E$2:$E$501))
A14: ARQ.08 | B14: Reboco exterior argamassa monocamada | C14: ARQ | D14: m² | I14: 22 | J14: =IF(AND(A14="",B14=""),"",IF(SUM(E14:H14)>0,SUM(E14:H14),I14)) -> 22 | K14: =IF(J14="","",ROUND(IF(SUM(E14:H14)>0,E14*(1+Config!$C$4)+F14*(1+Config!$C$5)+G14*(1+Config!$C$6)+H14*(1+Config!$C$7),I14*(1+Config!$C$8)),2)) -> 22.44 | M14: =IF(J14="","",IF(L14="",Config!$C$3,L14)) -> 0.2 | N14: =IF(K14="","",ROUND(K14*(1+M14),2)) -> 26.93 | O14: Referência de mercado Porto/Aveiro (BASE_PRECOS_2026) | Q14: Jun-2026 | R14: C | S14: =IF(A14="","",COUNTIF(Registo!$B$2:$B$501,A14)) -> 0 | T14: =IF(OR(A14="",S14=0),"",LOOKUP(2,1/(Registo!$B$2:$B$501=A14),Registo!$E$2:$E$501))
A15: ARQ.09 | B15: ETICS parede exterior (EPS 60mm + acabamento) | C15: ARQ | D15: m² | I15: 65 | J15: =IF(AND(A15="",B15=""),"",IF(SUM(E15:H15)>0,SUM(E15:H15),I15)) -> 65 | K15: =IF(J15="","",ROUND(IF(SUM(E15:H15)>0,E15*(1+Config!$C$4)+F15*(1+Config!$C$5)+G15*(1+Config!$C$6)+H15*(1+Config!$C$7),I15*(1+Config!$C$8)),2)) -> 66.3 | M15: =IF(J15="","",IF(L15="",Config!$C$3,L15)) -> 0.2 | N15: =IF(K15="","",ROUND(K15*(1+M15),2)) -> 79.56 | O15: Referência de mercado Porto/Aveiro (BASE_PRECOS_2026) | Q15: Jun-2026 | R15: C | S15: =IF(A15="","",COUNTIF(Registo!$B$2:$B$501,A15)) -> 0 | T15: =IF(OR(A15="",S15=0),"",LOOKUP(2,1/(Registo!$B$2:$B$501=A15),Registo!$E$2:$E$501))
A16: ARQ.10 | B16: ETICS parede exterior (EPS 80mm + acabamento) | C16: ARQ | D16: m² | I16: 72 | J16: =IF(AND(A16="",B16=""),"",IF(SUM(E16:H16)>0,SUM(E16:H16),I16)) -> 72 | K16: =IF(J16="","",ROUND(IF(SUM(E16:H16)>0,E16*(1+Config!$C$4)+F16*(1+Config!$C$5)+G16*(1+Config!$C$6)+H16*(1+Config!$C$7),I16*(1+Config!$C$8)),2)) -> 73.44 | M16: =IF(J16="","",IF(L16="",Config!$C$3,L16)) -> 0.2 | N16: =IF(K16="","",ROUND(K16*(1+M16),2)) -> 88.13 | O16: Referência de mercado Porto/Aveiro (BASE_PRECOS_2026) | Q16: Jun-2026 | R16: C | S16: =IF(A16="","",COUNTIF(Registo!$B$2:$B$501,A16)) -> 0 | T16: =IF(OR(A16="",S16=0),"",LOOKUP(2,1/(Registo!$B$2:$B$501=A16),Registo!$E$2:$E$501))
A17: ARQ.11 | B17: Revestimento cerâmico parede interior (colocação) | C17: ARQ | D17: m² | I17: 28 | J17: =IF(AND(A17="",B17=""),"",IF(SUM(E17:H17)>0,SUM(E17:H17),I17)) -> 28 | K17: =IF(J17="","",ROUND(IF(SUM(E17:H17)>0,E17*(1+Config!$C$4)+F17*(1+Config!$C$5)+G17*(1+Config!$C$6)+H17*(1+Config!$C$7),I17*(1+Config!$C$8)),2)) -> 28.56 | M17: =IF(J17="","",IF(L17="",Config!$C$3,L17)) -> 0.2 | N17: =IF(K17="","",ROUND(K17*(1+M17),2)) -> 34.27 | O17: Referência de mercado Porto/Aveiro (BASE_PRECOS_2026) | Q17: Jun-2026 | R17: C | S17: =IF(A17="","",COUNTIF(Registo!$B$2:$B$501,A17)) -> 0 | T17: =IF(OR(A17="",S17=0),"",LOOKUP(2,1/(Registo!$B$2:$B$501=A17),Registo!$E$2:$E$501))
A18: ARQ.12 | B18: Revestimento cerâmico parede exterior (colocação) | C18: ARQ | D18: m² | I18: 32 | J18: =IF(AND(A18="",B18=""),"",IF(SUM(E18:H18)>0,SUM(E18:H18),I18)) -> 32 | K18: =IF(J18="","",ROUND(IF(SUM(E18:H18)>0,E18*(1+Config!$C$4)+F18*(1+Config!$C$5)+G18*(1+Config!$C$6)+H18*(1+Config!$C$7),I18*(1+Config!$C$8)),2)) -> 32.64 | M18: =IF(J18="","",IF(L18="",Config!$C$3,L18)) -> 0.2 | N18: =IF(K18="","",ROUND(K18*(1+M18),2)) -> 39.17 | O18: Referência de mercado Porto/Aveiro (BASE_PRECOS_2026) | Q18: Jun-2026 | R18: C | S18: =IF(A18="","",COUNTIF(Registo!$B$2:$B$501,A18)) -> 0 | T18: =IF(OR(A18="",S18=0),"",LOOKUP(2,1/(Registo!$B$2:$B$501=A18),Registo!$E$2:$E$501))
... A36: ARQ.30 | B36: Guarda-corpo inox escovado | C36: ARQ | D36: m | I36: 320 | J36: =IF(AND(A36="",B36=""),"",IF(SUM(E36:H36)>0,SUM(E36:H36),I36)) -> 320 | K36: =IF(J36="","",ROUND(IF(SUM(E36:H36)>0,E36*(1+Config!$C$4)+F36*(1+Config!$C$5)+G36*(1+Config!$C$6)+H36*(1+Config!$C$7),I36*(1+Config!$C$8)),2)) -> 326.4 | M36: =IF(J36="","",IF(L36="",Config!$C$3,L36)) -> 0.2 | N36: =IF(K36="","",ROUND(K36*(1+M36),2)) -> 391.68 | O36: Referência de mercado Porto/Aveiro (BASE_PRECOS_2026) | Q36: Jun-2026 | R36: C | S36: =IF(A36="","",COUNTIF(Registo!$B$2:$B$501,A36)) -> 0 | T36: =IF(OR(A36="",S36=0),"",LOOKUP(2,1/(Registo!$B$2:$B$501=A36),Registo!$E$2:$E$501))
A37: ARQ.31 | B37: Demolição de parede interior em alvenaria existente, c/ ensacamento manual, transporte à mão e remoção a vazadouro | C37: ARQ | D37: m² | I37: 55 | J37: =IF(AND(A37="",B37=""),"",IF(SUM(E37:H37)>0,SUM(E37:H37),I37)) -> 55 | K37: =IF(J37="","",ROUND(IF(SUM(E37:H37)>0,E37*(1+Config!$C$4)+F37*(1+Config!$C$5)+G37*(1+Config!$C$6)+H37*(1+Config!$C$7),I37*(1+Config!$C$8)),2)) -> 56.1 | M37: =IF(J37="","",IF(L37="",Config!$C$3,L37)) -> 0.2 | N37: =IF(K37="","",ROUND(K37*(1+M37),2)) -> 67.32 | O37: Orçamento próprio (custo, antes de margem) | P37: Ribeira – remodelação (L99) | Q37: 2026 | R37: B | S37: =IF(A37="","",COUNTIF(Registo!$B$2:$B$501,A37)) -> 0 | T37: =IF(OR(A37="",S37=0),"",LOOKUP(2,1/(Registo!$B$2:$B$501=A37),Registo!$E$2:$E$501)) | U37: Inclui agravamento por acesso condicionado (transporte manual 100 m + escadaria, 1.º andar s/ elevador)
A38: ARQ.32 | B38: Abertura e fecho de vãos em alvenaria rebocada, incl. lintéis e regularização | C38: ARQ | D38: un | I38: 480 | J38: =IF(AND(A38="",B38=""),"",IF(SUM(E38:H38)>0,SUM(E38:H38),I38)) -> 480 | K38: =IF(J38="","",ROUND(IF(SUM(E38:H38)>0,E38*(1+Config!$C$4)+F38*(1+Config!$C$5)+G38*(1+Config!$C$6)+H38*(1+Config!$C$7),I38*(1+Config!$C$8)),2)) -> 489.6 | M38: =IF(J38="","",IF(L38="",Config!$C$3,L38)) -> 0.2 | N38: =IF(K38="","",ROUND(K38*(1+M38),2)) -> 587.52 | O38: Orçamento próprio (custo, antes de margem) | P38: Ribeira – remodelação (L99) | Q38: 2026 | R38: B | S38: =IF(A38="","",COUNTIF(Registo!$B$2:$B$501,A38)) -> 0 | T38: =IF(OR(A38="",S38=0),"",LOOKUP(2,1/(Registo!$B$2:$B$501=A38),Registo!$E$2:$E$501)) | U38: Inclui agravamento por acesso condicionado (transporte manual 100 m + escadaria, 1.º andar s/ elevador)
A39: ARQ.33 | B39: Parede em pladur standard BA13 c/ estrutura metálica galvanizada, juntas tratadas, pronta a pintar | C39: ARQ | D39: m² | I39: 58 | J39: =IF(AND(A39="",B39=""),"",IF(SUM(E39:H39)>0,SUM(E39:H39),I39)) -> 58 | K39: =IF(J39="","",ROUND(IF(SUM(E39:H39)>0,E39*(1+Config!$C$4)+F39*(1+Config!$C$5)+G39*(1+Config!$C$6)+H39*(1+Config!$C$7),I39*(1+Config!$C$8)),2)) -> 59.16 | M39: =IF(J39="","",IF(L39="",Config!$C$3,L39)) -> 0.2 | N39: =IF(K39="","",ROUND(K39*(1+M39),2)) -> 70.99 | O39: Orçamento próprio (custo, antes de margem) | P39: Ribeira – remodelação (L99) | Q39: 2026 | R39: B | S39: =IF(A39="","",COUNTIF(Registo!$B$2:$B$501,A39)) -> 0 | T39: =IF(OR(A39="",S39=0),"",LOOKUP(2,1/(Registo!$B$2:$B$501=A39),Registo!$E$2:$E$501)) | U39: Inclui agravamento por acesso condicionado (transporte manual 100 m + escadaria, 1.º andar s/ elevador)
A40: ARQ.34 | B40: Revestimento cerâmico em paredes de WC (fornecimento e aplicação), cimento-cola C2TES1 e betumação | C40: ARQ | D40: m² | I40: 52 | J40: =IF(AND(A40="",B40=""),"",IF(SUM(E40:H40)>0,SUM(E40:H40),I40)) -> 52 | K40: =IF(J40="","",ROUND(IF(SUM(E40:H40)>0,E40*(1+Config!$C$4)+F40*(1+Config!$C$5)+G40*(1+Config!$C$6)+H40*(1+Config!$C$7),I40*(1+Config!$C$8)),2)) -> 53.04 | M40: =IF(J40="","",IF(L40="",Config!$C$3,L40)) -> 0.2 | N40: =IF(K40="","",ROUND(K40*(1+M40),2)) -> 63.65 | O40: Orçamento próprio (custo, antes de margem) | P40: Ribeira – remodelação (L99) | Q40: 2026 | R40: B | S40: =IF(A40="","",COUNTIF(Registo!$B$2:$B$501,A40)) -> 0 | T40: =IF(OR(A40="",S40=0),"",LOOKUP(2,1/(Registo!$B$2:$B$501=A40),Registo!$E$2:$E$501)) | U40: Inclui agravamento por acesso condicionado (transporte manual 100 m + escadaria, 1.º andar s/ elevador)
A41: ARQ.35 | B41: Pladur hidrófugo H1 em zonas húmidas (paredes) | C41: ARQ | D41: m² | I41: 50 | J41: =IF(AND(A41="",B41=""),"",IF(SUM(E41:H41)>0,SUM(E41:H41),I41)) -> 50 | K41: =IF(J41="","",ROUND(IF(SUM(E41:H41)>0,E41*(1+Config!$C$4)+F41*(1+Config!$C$5)+G41*(1+Config!$C$6)+H41*(1+Config!$C$7),I41*(1+Config!$C$8)),2)) -> 51 | M41: =IF(J41="","",IF(L41="",Config!$C$3,L41)) -> 0.2 | N41: =IF(K41="","",ROUND(K41*(1+M41),2)) -> 61.2 | O41: Orçamento próprio (custo, antes de margem) | P41: Ribeira – remodelação (L99) | Q41: 2026 | R41: B | S41: =IF(A41="","",COUNTIF(Registo!$B$2:$B$501,A41)) -> 0 | T41: =IF(OR(A41="",S41=0),"",LOOKUP(2,1/(Registo!$B$2:$B$501=A41),Registo!$E$2:$E$501)) | U41: Inclui agravamento por acesso condicionado (transporte manual 100 m + escadaria, 1.º andar s/ elevador)
A42: ARQ.36 | B42: Impermeabilização com argamassa bicomponente (tipo Weber 824) em pavimento e zona de duche | C42: ARQ | D42: m² | I42: 28 | J42: =IF(AND(A42="",B42=""),"",IF(SUM(E42:H42)>0,SUM(E42:H42),I42)) -> 28 | K42: =IF(J42="","",ROUND(IF(SUM(E42:H42)>0,E42*(1+Config!$C$4)+F42*(1+Config!$C$5)+G42*(1+Config!$C$6)+H42*(1+Config!$C$7),I42*(1+Config!$C$8)),2)) -> 28.56 | M42: =IF(J42="","",IF(L42="",Config!$C$3,L42)) -> 0.2 | N42: =IF(K42="","",ROUND(K42*(1+M42),2)) -> 34.27 | O42: Orçamento próprio (custo, antes de margem) | P42: Ribeira – remodelação (L99) | Q42: 2026 | R42: B | S42: =IF(A42="","",COUNTIF(Registo!$B$2:$B$501,A42)) -> 0 | T42: =IF(OR(A42="",S42=0),"",LOOKUP(2,1/(Registo!$B$2:$B$501=A42),Registo!$E$2:$E$501)) | U42: Inclui agravamento por acesso condicionado (transporte manual 100 m + escadaria, 1.º andar s/ elevador)
A43: ARQ.37 | B43: Pavimento cerâmico em WC (fornecimento e aplicação), cimento-cola C2TES1 e betumação | C43: ARQ | D43: m² | I43: 52 | J43: =IF(AND(A43="",B43=""),"",IF(SUM(E43:H43)>0,SUM(E43:H43),I43)) -> 52 | K43: =IF(J43="","",ROUND(IF(SUM(E43:H43)>0,E43*(1+Config!$C$4)+F43*(1+Config!$C$5)+G43*(1+Config!$C$6)+H43*(1+Config!$C$7),I43*(1+Config!$C$8)),2)) -> 53.04 | M43: =IF(J43="","",IF(L43="",Config!$C$3,L43)) -> 0.2 | N43: =IF(K43="","",ROUND(K43*(1+M43),2)) -> 63.65 | O43: Orçamento próprio (custo, antes de margem) | P43: Ribeira – remodelação (L99) | Q43: 2026 | R43: B | S43: =IF(A43="","",COUNTIF(Registo!$B$2:$B$501,A43)) -> 0 | T43: =IF(OR(A43="",S43=0),"",LOOKUP(2,1/(Registo!$B$2:$B$501=A43),Registo!$E$2:$E$501)) | U43: Inclui agravamento por acesso condicionado (transporte manual 100 m + escadaria, 1.º andar s/ elevador)
A44: ARQ.38 | B44: Teto falso em pladur BA13 c/ estrutura suspensa, nivelamento e juntas | C44: ARQ | D44: m² | I44: 62 | J44: =IF(AND(A44="",B44=""),"",IF(SUM(E44:H44)>0,SUM(E44:H44),I44)) -> 62 | K44: =IF(J44="","",ROUND(IF(SUM(E44:H44)>0,E44*(1+Config!$C$4)+F44*(1+Config!$C$5)+G44*(1+Config!$C$6)+H44*(1+Config!$C$7),I44*(1+Config!$C$8)),2)) -> 63.24 | M44: =IF(J44="","",IF(L44="",Config!$C$3,L44)) -> 0.2 | N44: =IF(K44="","",ROUND(K44*(1+M44),2)) -> 75.89 | O44: Orçamento próprio (custo, antes de margem) | P44: Ribeira – remodelação (L99) | Q44: 2026 | R44: B | S44: =IF(A44="","",COUNTIF(Registo!$B$2:$B$501,A44)) -> 0 | T44: =IF(OR(A44="",S44=0),"",LOOKUP(2,1/(Registo!$B$2:$B$501=A44),Registo!$E$2:$E$501)) | U44: Inclui agravamento por acesso condicionado (transporte manual 100 m + escadaria, 1.º andar s/ elevador)
A45: ARQ.39 | B45: Teto falso em pladur hidrófugo H1 em zonas húmidas | C45: ARQ | D45: m² | I45: 55 | J45: =IF(AND(A45="",B45=""),"",IF(SUM(E45:H45)>0,SUM(E45:H45),I45)) -> 55 | K45: =IF(J45="","",ROUND(IF(SUM(E45:H45)>0,E45*(1+Config!$C$4)+F45*(1+Config!$C$5)+G45*(1+Config!$C$6)+H45*(1+Config!$C$7),I45*(1+Config!$C$8)),2)) -> 56.1 | M45: =IF(J45="","",IF(L45="",Config!$C$3,L45)) -> 0.2 | N45: =IF(K45="","",ROUND(K45*(1+M45),2)) -> 67.32 | O45: Orçamento próprio (custo, antes de margem) | P45: Ribeira – remodelação (L99) | Q45: 2026 | R45: B | S45: =IF(A45="","",COUNTIF(Registo!$B$2:$B$501,A45)) -> 0 | T45: =IF(OR(A45="",S45=0),"",LOOKUP(2,1/(Registo!$B$2:$B$501=A45),Registo!$E$2:$E$501)) | U45: Inclui agravamento por acesso condicionado (transporte manual 100 m + escadaria, 1.º andar s/ elevador)
A46: ARQ.40 | B46: Pintura de paredes e tetos: primário + 2 demãos de tinta acrílica lavável | C46: ARQ | D46: m² | I46: 20 | J46: =IF(AND(A46="",B46=""),"",IF(SUM(E46:H46)>0,SUM(E46:H46),I46)) -> 20 | K46: =IF(J46="","",ROUND(IF(SUM(E46:H46)>0,E46*(1+Config!$C$4)+F46*(1+Config!$C$5)+G46*(1+Config!$C$6)+H46*(1+Config!$C$7),I46*(1+Config!$C$8)),2)) -> 20.4 | M46: =IF(J46="","",IF(L46="",Config!$C$3,L46)) -> 0.2 | N46: =IF(K46="","",ROUND(K46*(1+M46),2)) -> 24.48 | O46: Orçamento próprio (custo, antes de margem) | P46: Ribeira – remodelação (L99) | Q46: 2026 | R46: B | S46: =IF(A46="","",COUNTIF(Registo!$B$2:$B$501,A46)) -> 0 | T46: =IF(OR(A46="",S46=0),"",LOOKUP(2,1/(Registo!$B$2:$B$501=A46),Registo!$E$2:$E$501)) | U46: Inclui agravamento por acesso condicionado (transporte manual 100 m + escadaria, 1.º andar s/ elevador)
A47: ARQ.41 | B47: OSB 10 mm para reforço da base de pavimento flutuante | C47: ARQ | D47: m² | I47: 48 | J47: =IF(AND(A47="",B47=""),"",IF(SUM(E47:H47)>0,SUM(E47:H47),I47)) -> 48 | K47: =IF(J47="","",ROUND(IF(SUM(E47:H47)>0,E47*(1+Config!$C$4)+F47*(1+Config!$C$5)+G47*(1+Config!$C$6)+H47*(1+Config!$C$7),I47*(1+Config!$C$8)),2)) -> 48.96 | M47: =IF(J47="","",IF(L47="",Config!$C$3,L47)) -> 0.2 | N47: =IF(K47="","",ROUND(K47*(1+M47),2)) -> 58.75 | O47: Orçamento próprio (custo, antes de margem) | P47: Ribeira – remodelação (L99) | Q47: 2026 | R47: B | S47: =IF(A47="","",COUNTIF(Registo!$B$2:$B$501,A47)) -> 0 | T47: =IF(OR(A47="",S47=0),"",LOOKUP(2,1/(Registo!$B$2:$B$501=A47),Registo!$E$2:$E$501)) | U47: Inclui agravamento por acesso condicionado (transporte manual 100 m + escadaria, 1.º andar s/ elevador)
A48: ARQ.42 | B48: Pavimento laminado AC4 Classe 32, 8 mm, click, c/ manta acústica e remates | C48: ARQ | D48: m² | I48: 54 | J48: =IF(AND(A48="",B48=""),"",IF(SUM(E48:H48)>0,SUM(E48:H48),I48)) -> 54 | K48: =IF(J48="","",ROUND(IF(SUM(E48:H48)>0,E48*(1+Config!$C$4)+F48*(1+Config!$C$5)+G48*(1+Config!$C$6)+H48*(1+Config!$C$7),I48*(1+Config!$C$8)),2)) -> 55.08 | M48: =IF(J48="","",IF(L48="",Config!$C$3,L48)) -> 0.2 | N48: =IF(K48="","",ROUND(K48*(1+M48),2)) -> 66.1 | O48: Orçamento próprio (custo, antes de margem) | P48: Ribeira – remodelação (L99) | Q48: 2026 | R48: B | S48: =IF(A48="","",COUNTIF(Registo!$B$2:$B$501,A48)) -> 0 | T48: =IF(OR(A48="",S48=0),"",LOOKUP(2,1/(Registo!$B$2:$B$501=A48),Registo!$E$2:$E$501)) | U48: Inclui agravamento por acesso condicionado (transporte manual 100 m + escadaria, 1.º andar s/ elevador)
A49: EST.01 | B49: Betão de limpeza C12/15 | C49: EST | D49: m³ | I49: 95 | J49: =IF(AND(A49="",B49=""),"",IF(SUM(E49:H49)>0,SUM(E49:H49),I49)) -> 95 | K49: =IF(J49="","",ROUND(IF(SUM(E49:H49)>0,E49*(1+Config!$C$4)+F49*(1+Config!$C$5)+G49*(1+Config!$C$6)+H49*(1+Config!$C$7),I49*(1+Config!$C$8)),2)) -> 96.9 | M49: =IF(J49="","",IF(L49="",Config!$C$3,L49)) -> 0.2 | N49: =IF(K49="","",ROUND(K49*(1+M49),2)) -> 116.28 | O49: Referência de mercado Porto/Aveiro (BASE_PRECOS_2026) | Q49: Jun-2026 | R49: C | S49: =IF(A49="","",COUNTIF(Registo!$B$2:$B$501,A49)) -> 0 | T49: =IF(OR(A49="",S49=0),"",LOOKUP(2,1/(Registo!$B$2:$B$501=A49),Registo!$E$2:$E$501))
A50: EST.02 | B50: Betão em fundações C25/30 (exec. c/ bomba) | C50: EST | D50: m³ | I50: 145 | J50: =IF(AND(A50="",B50=""),"",IF(SUM(E50:H50)>0,SUM(E50:H50),I50)) -> 145 | K50: =IF(J50="","",ROUND(IF(SUM(E50:H50)>0,E50*(1+Config!$C$4)+F50*(1+Config!$C$5)+G50*(1+Config!$C$6)+H50*(1+Config!$C$7),I50*(1+Config!$C$8)),2)) -> 147.9 | M50: =IF(J50="","",IF(L50="",Config!$C$3,L50)) -> 0.2 | N50: =IF(K50="","",ROUND(K50*(1+M50),2)) -> 177.48 | O50: Referência de mercado Porto/Aveiro (BASE_PRECOS_2026) | Q50: Jun-2026 | R50: C | S50: =IF(A50="","",COUNTIF(Registo!$B$2:$B$501,A50)) -> 0 | T50: =IF(OR(A50="",S50=0),"",LOOKUP(2,1/(Registo!$B$2:$B$501=A50),Registo!$E$2:$E$501))
A51: EST.03 | B51: Betão em pilares C25/30 | C51: EST | D51: m³ | I51: 165 | J51: =IF(AND(A51="",B51=""),"",IF(SUM(E51:H51)>0,SUM(E51:H51),I51)) -> 165 | K51: =IF(J51="","",ROUND(IF(SUM(E51:H51)>0,E51*(1+Config!$C$4)+F51*(1+Config!$C$5)+G51*(1+Config!$C$6)+H51*(1+Config!$C$7),I51*(1+Config!$C$8)),2)) -> 168.3 | M51: =IF(J51="","",IF(L51="",Config!$C$3,L51)) -> 0.2 | N51: =IF(K51="","",ROUND(K51*(1+M51),2)) -> 201.96 | O51: Referência de mercado Porto/Aveiro (BASE_PRECOS_2026) | Q51: Jun-2026 | R51: C | S51: =IF(A51="","",COUNTIF(Registo!$B$2:$B$501,A51)) -> 0 | T51: =IF(OR(A51="",S51=0),"",LOOKUP(2,1/(Registo!$B$2:$B$501=A51),Registo!$E$2:$E$501))
A52: EST.04 | B52: Betão em vigas C25/30 | C52: EST | D52: m³ | I52: 155 | J52: =IF(AND(A52="",B52=""),"",IF(SUM(E52:H52)>0,SUM(E52:H52),I52)) -> 155 | K52: =IF(J52="","",ROUND(IF(SUM(E52:H52)>0,E52*(1+Config!$C$4)+F52*(1+Config!$C$5)+G52*(1+Config!$C$6)+H52*(1+Config!$C$7),I52*(1+Config!$C$8)),2)) -> 158.1 | M52: =IF(J52="","",IF(L52="",Config!$C$3,L52)) -> 0.2 | N52: =IF(K52="","",ROUND(K52*(1+M52),2)) -> 189.72 | O52: Referência de mercado Porto/Aveiro (BASE_PRECOS_2026) | Q52: Jun-2026 | R52: C | S52: =IF(A52="","",COUNTIF(Registo!$B$2:$B$501,A52)) -> 0 | T52: =IF(OR(A52="",S52=0),"",LOOKUP(2,1/(Registo!$B$2:$B$501=A52),Registo!$E$2:$E$501))
A53: EST.05 | B53: Betão em laje maciça C25/30 | C53: EST | D53: m³ | I53: 150 | J53: =IF(AND(A53="",B53=""),"",IF(SUM(E53:H53)>0,SUM(E53:H53),I53)) -> 150 | K53: =IF(J53="","",ROUND(IF(SUM(E53:H53)>0,E53*(1+Config!$C$4)+F53*(1+Config!$C$5)+G53*(1+Config!$C$6)+H53*(1+Config!$C$7),I53*(1+Config!$C$8)),2)) -> 153 | M53: =IF(J53="","",IF(L53="",Config!$C$3,L53)) -> 0.2 | N53: =IF(K53="","",ROUND(K53*(1+M53),2)) -> 183.6 | O53: Referência de mercado Porto/Aveiro (BASE_PRECOS_2026) | Q53: Jun-2026 | R53: C | S53: =IF(A53="","",COUNTIF(Registo!$B$2:$B$501,A53)) -> 0 | T53: =IF(OR(A53="",S53=0),"",LOOKUP(2,1/(Registo!$B$2:$B$501=A53),Registo!$E$2:$E$501))
A54: EST.06 | B54: Betão em laje aligeirada (PAVICER) C25/30 | C54: EST | D54: m² | I54: 62 | J54: =IF(AND(A54="",B54=""),"",IF(SUM(E54:H54)>0,SUM(E54:H54),I54)) -> 62 | K54: =IF(J54="","",ROUND(IF(SUM(E54:H54)>0,E54*(1+Config!$C$4)+F54*(1+Config!$C$5)+G54*(1+Config!$C$6)+H54*(1+Config!$C$7),I54*(1+Config!$C$8)),2)) -> 63.24 | M54: =IF(J54="","",IF(L54="",Config!$C$3,L54)) -> 0.2 | N54: =IF(K54="","",ROUND(K54*(1+M54),2)) -> 75.89 | O54: Referência de mercado Porto/Aveiro (BASE_PRECOS_2026) | Q54: Jun-2026 | R54: C | S54: =IF(A54="","",COUNTIF(Registo!$B$2:$B$501,A54)) -> 0 | T54: =IF(OR(A54="",S54=0),"",LOOKUP(2,1/(Registo!$B$2:$B$501=A54),Registo!$E$2:$E$501))
A55: EST.07 | B55: Betão em escadas C25/30 | C55: EST | D55: m³ | I55: 175 | J55: =IF(AND(A55="",B55=""),"",IF(SUM(E55:H55)>0,SUM(E55:H55),I55)) -> 175 | K55: =IF(J55="","",ROUND(IF(SUM(E55:H55)>0,E55*(1+Config!$C$4)+F55*(1+Config!$C$5)+G55*(1+Config!$C$6)+H55*(1+Config!$C$7),I55*(1+Config!$C$8)),2)) -> 178.5 | M55: =IF(J55="","",IF(L55="",Config!$C$3,L55)) -> 0.2 | N55: =IF(K55="","",ROUND(K55*(1+M55),2)) -> 214.2 | O55: Referência de mercado Porto/Aveiro (BASE_PRECOS_2026) | Q55: Jun-2026 | R55: C | S55: =IF(A55="","",COUNTIF(Registo!$B$2:$B$501,A55)) -> 0 | T55: =IF(OR(A55="",S55=0),"",LOOKUP(2,1/(Registo!$B$2:$B$501=A55),Registo!$E$2:$E$501))
A56: EST.08 | B56: Aço A400 em varão (fornecimento + colocação) | C56: EST | D56: kg | I56: 1.45 | J56: =IF(AND(A56="",B56=""),"",IF(SUM(E56:H56)>0,SUM(E56:H56),I56)) -> 1.45 | K56: =IF(J56="","",ROUND(IF(SUM(E56:H56)>0,E56*(1+Config!$C$4)+F56*(1+Config!$C$5)+G56*(1+Config!$C$6)+H56*(1+Config!$C$7),I56*(1+Config!$C$8)),2)) -> 1.48 | M56: =IF(J56="","",IF(L56="",Config!$C$3,L56)) -> 0.2 | N56: =IF(K56="","",ROUND(K56*(1+M56),2)) -> 1.78 | O56: Referência de mercado Porto/Aveiro (BASE_PRECOS_2026) | Q56: Jun-2026 | R56: C | S56: =IF(A56="","",COUNTIF(Registo!$B$2:$B$501,A56)) -> 0 | T56: =IF(OR(A56="",S56=0),"",LOOKUP(2,1/(Registo!$B$2:$B$501=A56),Registo!$E$2:$E$501))
A57: EST.09 | B57: Aço A500 em varão (fornecimento + colocação) | C57: EST | D57: kg | I57: 1.55 | J57: =IF(AND(A57="",B57=""),"",IF(SUM(E57:H57)>0,SUM(E57:H57),I57)) -> 1.55 | K57: =IF(J57="","",ROUND(IF(SUM(E57:H57)>0,E57*(1+Config!$C$4)+F57*(1+Config!$C$5)+G57*(1+Config!$C$6)+H57*(1+Config!$C$7),I57*(1+Config!$C$8)),2)) -> 1.58 | M57: =IF(J57="","",IF(L57="",Config!$C$3,L57)) -> 0.2 | N57: =IF(K57="","",ROUND(K57*(1+M57),2)) -> 1.9 | O57: Referência de mercado Porto/Aveiro (BASE_PRECOS_2026) | Q57: Jun-2026 | R57: C | S57: =IF(A57="","",COUNTIF(Registo!$B$2:$B$501,A57)) -> 0 | T57: =IF(OR(A57="",S57=0),"",LOOKUP(2,1/(Registo!$B$2:$B$501=A57),Registo!$E$2:$E$501))
A58: EST.10 | B58: Cofragem recuperável em pilares | C58: EST | D58: m² | I58: 22 | J58: =IF(AND(A58="",B58=""),"",IF(SUM(E58:H58)>0,SUM(E58:H58),I58)) -> 22 | K58: =IF(J58="","",ROUND(IF(SUM(E58:H58)>0,E58*(1+Config!$C$4)+F58*(1+Config!$C$5)+G58*(1+Config!$C$6)+H58*(1+Config!$C$7),I58*(1+Config!$C$8)),2)) -> 22.44 | M58: =IF(J58="","",IF(L58="",Config!$C$3,L58)) -> 0.2 | N58: =IF(K58="","",ROUND(K58*(1+M58),2)) -> 26.93 | O58: Referência de mercado Porto/Aveiro (BASE_PRECOS_2026) | Q58: Jun-2026 | R58: C | S58: =IF(A58="","",COUNTIF(Registo!$B$2:$B$501,A58)) -> 0 | T58: =IF(OR(A58="",S58=0),"",LOOKUP(2,1/(Registo!$B$2:$B$501=A58),Registo!$E$2:$E$501))
A59: EST.11 | B59: Cofragem recuperável em vigas | C59: EST | D59: m² | I59: 28 | J59: =IF(AND(A59="",B59=""),"",IF(SUM(E59:H59)>0,SUM(E59:H59),I59)) -> 28 | K59: =IF(J59="","",ROUND(IF(SUM(E59:H59)>0,E59*(1+Config!$C$4)+F59*(1+Config!$C$5)+G59*(1+Config!$C$6)+H59*(1+Config!$C$7),I59*(1+Config!$C$8)),2)) -> 28.56 | M59: =IF(J59="","",IF(L59="",Config!$C$3,L59)) -> 0.2 | N59: =IF(K59="","",ROUND(K59*(1+M59),2)) -> 34.27 | O59: Referência de mercado Porto/Aveiro (BASE_PRECOS_2026) | Q59: Jun-2026 | R59: C | S59: =IF(A59="","",COUNTIF(Registo!$B$2:$B$501,A59)) -> 0 | T59: =IF(OR(A59="",S59=0),"",LOOKUP(2,1/(Registo!$B$2:$B$501=A59),Registo!$E$2:$E$501))
A60: EST.12 | B60: Cofragem recuperável em lajes | C60: EST | D60: m² | I60: 18 | J60: =IF(AND(A60="",B60=""),"",IF(SUM(E60:H60)>0,SUM(E60:H60),I60)) -> 18 | K60: =IF(J60="","",ROUND(IF(SUM(E60:H60)>0,E60*(1+Config!$C$4)+F60*(1+Config!$C$5)+G60*(1+Config!$C$6)+H60*(1+Config!$C$7),I60*(1+Config!$C$8)),2)) -> 18.36 | M60: =IF(J60="","",IF(L60="",Config!$C$3,L60)) -> 0.2 | N60: =IF(K60="","",ROUND(K60*(1+M60),2)) -> 22.03 | O60: Referência de mercado Porto/Aveiro (BASE_PRECOS_2026) | Q60: Jun-2026 | R60: C | S60: =IF(A60="","",COUNTIF(Registo!$B$2:$B$501,A60)) -> 0 | T60: =IF(OR(A60="",S60=0),"",LOOKUP(2,1/(Registo!$B$2:$B$501=A60),Registo!$E$2:$E$501))
... A77: HID.15 | B77: Depósito AQS 200l c/ serpentina | C77: HID | D77: un | I77: 1100 | J77: =IF(AND(A77="",B77=""),"",IF(SUM(E77:H77)>0,SUM(E77:H77),I77)) -> 1100 | K77: =IF(J77="","",ROUND(IF(SUM(E77:H77)>0,E77*(1+Config!$C$4)+F77*(1+Config!$C$5)+G77*(1+Config!$C$6)+H77*(1+Config!$C$7),I77*(1+Config!$C$8)),2)) -> 1122 | M77: =IF(J77="","",IF(L77="",Config!$C$3,L77)) -> 0.2 | N77: =IF(K77="","",ROUND(K77*(1+M77),2)) -> 1346.4 | O77: Referência de mercado Porto/Aveiro (BASE_PRECOS_2026) | Q77: Jun-2026 | R77: C | S77: =IF(A77="","",COUNTIF(Registo!$B$2:$B$501,A77)) -> 0 | T77: =IF(OR(A77="",S77=0),"",LOOKUP(2,1/(Registo!$B$2:$B$501=A77),Registo!$E$2:$E$501))
A78: HID.16 | B78: Remoção de loiças sanitárias existentes (desmontagem cuidada, corte de ligações, transporte) | C78: HID | D78: vg | I78: 200 | J78: =IF(AND(A78="",B78=""),"",IF(SUM(E78:H78)>0,SUM(E78:H78),I78)) -> 200 | K78: =IF(J78="","",ROUND(IF(SUM(E78:H78)>0,E78*(1+Config!$C$4)+F78*(1+Config!$C$5)+G78*(1+Config!$C$6)+H78*(1+Config!$C$7),I78*(1+Config!$C$8)),2)) -> 204 | M78: =IF(J78="","",IF(L78="",Config!$C$3,L78)) -> 0.2 | N78: =IF(K78="","",ROUND(K78*(1+M78),2)) -> 244.8 | O78: Orçamento próprio (custo, antes de margem) | P78: Ribeira – remodelação (L99) | Q78: 2026 | R78: B | S78: =IF(A78="","",COUNTIF(Registo!$B$2:$B$501,A78)) -> 0 | T78: =IF(OR(A78="",S78=0),"",LOOKUP(2,1/(Registo!$B$2:$B$501=A78),Registo!$E$2:$E$501)) | U78: Inclui agravamento por acesso condicionado (transporte manual 100 m + escadaria, 1.º andar s/ elevador)
A79: HID.17 | B79: Conjunto sanita + autoclismo + assento (gama média) | C79: HID | D79: un | I79: 340 | J79: =IF(AND(A79="",B79=""),"",IF(SUM(E79:H79)>0,SUM(E79:H79),I79)) -> 340 | K79: =IF(J79="","",ROUND(IF(SUM(E79:H79)>0,E79*(1+Config!$C$4)+F79*(1+Config!$C$5)+G79*(1+Config!$C$6)+H79*(1+Config!$C$7),I79*(1+Config!$C$8)),2)) -> 346.8 | M79: =IF(J79="","",IF(L79="",Config!$C$3,L79)) -> 0.2 | N79: =IF(K79="","",ROUND(K79*(1+M79),2)) -> 416.16 | O79: Orçamento próprio (custo, antes de margem) | P79: Ribeira – remodelação (L99) | Q79: 2026 | R79: B | S79: =IF(A79="","",COUNTIF(Registo!$B$2:$B$501,A79)) -> 0 | T79: =IF(OR(A79="",S79=0),"",LOOKUP(2,1/(Registo!$B$2:$B$501=A79),Registo!$E$2:$E$501)) | U79: Inclui agravamento por acesso condicionado (transporte manual 100 m + escadaria, 1.º andar s/ elevador)
A80: HID.18 | B80: Móvel WC 58x48 cm c/ lavatório de pousar e bancada | C80: HID | D80: un | I80: 590 | J80: =IF(AND(A80="",B80=""),"",IF(SUM(E80:H80)>0,SUM(E80:H80),I80)) -> 590 | K80: =IF(J80="","",ROUND(IF(SUM(E80:H80)>0,E80*(1+Config!$C$4)+F80*(1+Config!$C$5)+G80*(1+Config!$C$6)+H80*(1+Config!$C$7),I80*(1+Config!$C$8)),2)) -> 601.8 | M80: =IF(J80="","",IF(L80="",Config!$C$3,L80)) -> 0.2 | N80: =IF(K80="","",ROUND(K80*(1+M80),2)) -> 722.16 | O80: Orçamento próprio (custo, antes de margem) | P80: Ribeira – remodelação (L99) | Q80: 2026 | R80: B | S80: =IF(A80="","",COUNTIF(Registo!$B$2:$B$501,A80)) -> 0 | T80: =IF(OR(A80="",S80=0),"",LOOKUP(2,1/(Registo!$B$2:$B$501=A80),Registo!$E$2:$E$501)) | U80: Inclui agravamento por acesso condicionado (transporte manual 100 m + escadaria, 1.º andar s/ elevador)
A81: HID.19 | B81: Base de duche em resina antiderrapante 70x120 cm | C81: HID | D81: un | I81: 460 | J81: =IF(AND(A81="",B81=""),"",IF(SUM(E81:H81)>0,SUM(E81:H81),I81)) -> 460 | K81: =IF(J81="","",ROUND(IF(SUM(E81:H81)>0,E81*(1+Config!$C$4)+F81*(1+Config!$C$5)+G81*(1+Config!$C$6)+H81*(1+Config!$C$7),I81*(1+Config!$C$8)),2)) -> 469.2 | M81: =IF(J81="","",IF(L81="",Config!$C$3,L81)) -> 0.2 | N81: =IF(K81="","",ROUND(K81*(1+M81),2)) -> 563.04 | O81: Orçamento próprio (custo, antes de margem) | P81: Ribeira – remodelação (L99) | Q81: 2026 | R81: B | S81: =IF(A81="","",COUNTIF(Registo!$B$2:$B$501,A81)) -> 0 | T81: =IF(OR(A81="",S81=0),"",LOOKUP(2,1/(Registo!$B$2:$B$501=A81),Registo!$E$2:$E$501)) | U81: Inclui agravamento por acesso condicionado (transporte manual 100 m + escadaria, 1.º andar s/ elevador)
A82: HID.20 | B82: Resguardo frontal de duche 120x185 cm vidro transparente | C82: HID | D82: un | I82: 510 | J82: =IF(AND(A82="",B82=""),"",IF(SUM(E82:H82)>0,SUM(E82:H82),I82)) -> 510 | K82: =IF(J82="","",ROUND(IF(SUM(E82:H82)>0,E82*(1+Config!$C$4)+F82*(1+Config!$C$5)+G82*(1+Config!$C$6)+H82*(1+Config!$C$7),I82*(1+Config!$C$8)),2)) -> 520.2 | M82: =IF(J82="","",IF(L82="",Config!$C$3,L82)) -> 0.2 | N82: =IF(K82="","",ROUND(K82*(1+M82),2)) -> 624.24 | O82: Orçamento próprio (custo, antes de margem) | P82: Ribeira – remodelação (L99) | Q82: 2026 | R82: B | S82: =IF(A82="","",COUNTIF(Registo!$B$2:$B$501,A82)) -> 0 | T82: =IF(OR(A82="",S82=0),"",LOOKUP(2,1/(Registo!$B$2:$B$501=A82),Registo!$E$2:$E$501)) | U82: Inclui agravamento por acesso condicionado (transporte manual 100 m + escadaria, 1.º andar s/ elevador)
A83: HID.21 | B83: Torneira de lavatório (gama média) | C83: HID | D83: un | I83: 100 | J83: =IF(AND(A83="",B83=""),"",IF(SUM(E83:H83)>0,SUM(E83:H83),I83)) -> 100 | K83: =IF(J83="","",ROUND(IF(SUM(E83:H83)>0,E83*(1+Config!$C$4)+F83*(1+Config!$C$5)+G83*(1+Config!$C$6)+H83*(1+Config!$C$7),I83*(1+Config!$C$8)),2)) -> 102 | M83: =IF(J83="","",IF(L83="",Config!$C$3,L83)) -> 0.2 | N83: =IF(K83="","",ROUND(K83*(1+M83),2)) -> 122.4 | O83: Orçamento próprio (custo, antes de margem) | P83: Ribeira – remodelação (L99) | Q83: 2026 | R83: B | S83: =IF(A83="","",COUNTIF(Registo!$B$2:$B$501,A83)) -> 0 | T83: =IF(OR(A83="",S83=0),"",LOOKUP(2,1/(Registo!$B$2:$B$501=A83),Registo!$E$2:$E$501)) | U83: Inclui agravamento por acesso condicionado (transporte manual 100 m + escadaria, 1.º andar s/ elevador)
A84: HID.22 | B84: Chuveiro c/ bicha e rampa telescópica | C84: HID | D84: un | I84: 120 | J84: =IF(AND(A84="",B84=""),"",IF(SUM(E84:H84)>0,SUM(E84:H84),I84)) -> 120 | K84: =IF(J84="","",ROUND(IF(SUM(E84:H84)>0,E84*(1+Config!$C$4)+F84*(1+Config!$C$5)+G84*(1+Config!$C$6)+H84*(1+Config!$C$7),I84*(1+Config!$C$8)),2)) -> 122.4 | M84: =IF(J84="","",IF(L84="",Config!$C$3,L84)) -> 0.2 | N84: =IF(K84="","",ROUND(K84*(1+M84),2)) -> 146.88 | O84: Orçamento próprio (custo, antes de margem) | P84: Ribeira – remodelação (L99) | Q84: 2026 | R84: B | S84: =IF(A84="","",COUNTIF(Registo!$B$2:$B$501,A84)) -> 0 | T84: =IF(OR(A84="",S84=0),"",LOOKUP(2,1/(Registo!$B$2:$B$501=A84),Registo!$E$2:$E$501)) | U84: Inclui agravamento por acesso condicionado (transporte manual 100 m + escadaria, 1.º andar s/ elevador)
A85: HID.23 | B85: Rede de águas quente e fria em multicamada (1 WC), incl. acessórios, isolamento e ligações | C85: HID | D85: vg | I85: 1850 | J85: =IF(AND(A85="",B85=""),"",IF(SUM(E85:H85)>0,SUM(E85:H85),I85)) -> 1850 | K85: =IF(J85="","",ROUND(IF(SUM(E85:H85)>0,E85*(1+Config!$C$4)+F85*(1+Config!$C$5)+G85*(1+Config!$C$6)+H85*(1+Config!$C$7),I85*(1+Config!$C$8)),2)) -> 1887 | M85: =IF(J85="","",IF(L85="",Config!$C$3,L85)) -> 0.2 | N85: =IF(K85="","",ROUND(K85*(1+M85),2)) -> 2264.4 | O85: Orçamento próprio (custo, antes de margem) | P85: Ribeira – remodelação (L99) | Q85: 2026 | R85: B | S85: =IF(A85="","",COUNTIF(Registo!$B$2:$B$501,A85)) -> 0 | T85: =IF(OR(A85="",S85=0),"",LOOKUP(2,1/(Registo!$B$2:$B$501=A85),Registo!$E$2:$E$501)) | U85: Inclui agravamento por acesso condicionado (transporte manual 100 m + escadaria, 1.º andar s/ elevador)
A86: HID.24 | B86: Válvulas, sifões, flexíveis e acessórios de acabamento (1 WC) | C86: HID | D86: vg | I86: 380 | J86: =IF(AND(A86="",B86=""),"",IF(SUM(E86:H86)>0,SUM(E86:H86),I86)) -> 380 | K86: =IF(J86="","",ROUND(IF(SUM(E86:H86)>0,E86*(1+Config!$C$4)+F86*(1+Config!$C$5)+G86*(1+Config!$C$6)+H86*(1+Config!$C$7),I86*(1+Config!$C$8)),2)) -> 387.6 | M86: =IF(J86="","",IF(L86="",Config!$C$3,L86)) -> 0.2 | N86: =IF(K86="","",ROUND(K86*(1+M86),2)) -> 465.12 | O86: Orçamento próprio (custo, antes de margem) | P86: Ribeira – remodelação (L99) | Q86: 2026 | R86: B | S86: =IF(A86="","",COUNTIF(Registo!$B$2:$B$501,A86)) -> 0 | T86: =IF(OR(A86="",S86=0),"",LOOKUP(2,1/(Registo!$B$2:$B$501=A86),Registo!$E$2:$E$501)) | U86: Inclui agravamento por acesso condicionado (transporte manual 100 m + escadaria, 1.º andar s/ elevador)
A87: HID.25 | B87: Ensaios de estanquidade e colocação em funcionamento | C87: HID | D87: vg | I87: 200 | J87: =IF(AND(A87="",B87=""),"",IF(SUM(E87:H87)>0,SUM(E87:H87),I87)) -> 200 | K87: =IF(J87="","",ROUND(IF(SUM(E87:H87)>0,E87*(1+Config!$C$4)+F87*(1+Config!$C$5)+G87*(1+Config!$C$6)+H87*(1+Config!$C$7),I87*(1+Config!$C$8)),2)) -> 204 | M87: =IF(J87="","",IF(L87="",Config!$C$3,L87)) -> 0.2 | N87: =IF(K87="","",ROUND(K87*(1+M87),2)) -> 244.8 | O87: Orçamento próprio (custo, antes de margem) | P87: Ribeira – remodelação (L99) | Q87: 2026 | R87: B | S87: =IF(A87="","",COUNTIF(Registo!$B$2:$B$501,A87)) -> 0 | T87: =IF(OR(A87="",S87=0),"",LOOKUP(2,1/(Registo!$B$2:$B$501=A87),Registo!$E$2:$E$501)) | U87: Inclui agravamento por acesso condicionado (transporte manual 100 m + escadaria, 1.º andar s/ elevador)
A88: ESG.01 | B88: Rede de drenagem doméstica em PVC série reforçada (1 WC), incl. caixas sifonadas | C88: ESG | D88: vg | I88: 1250 | J88: =IF(AND(A88="",B88=""),"",IF(SUM(E88:H88)>0,SUM(E88:H88),I88)) -> 1250 | K88: =IF(J88="","",ROUND(IF(SUM(E88:H88)>0,E88*(1+Config!$C$4)+F88*(1+Config!$C$5)+G88*(1+Config!$C$6)+H88*(1+Config!$C$7),I88*(1+Config!$C$8)),2)) -> 1275 | M88: =IF(J88="","",IF(L88="",Config!$C$3,L88)) -> 0.2 | N88: =IF(K88="","",ROUND(K88*(1+M88),2)) -> 1530 | O88: Orçamento próprio (custo, antes de margem) | P88: Ribeira – remodelação (L99) | Q88: 2026 | R88: B | S88: =IF(A88="","",COUNTIF(Registo!$B$2:$B$501,A88)) -> 0 | T88: =IF(OR(A88="",S88=0),"",LOOKUP(2,1/(Registo!$B$2:$B$501=A88),Registo!$E$2:$E$501)) | U88: Inclui agravamento por acesso condicionado (transporte manual 100 m + escadaria, 1.º andar s/ elevador)
A89: HID.05 | B89: Tubo queda PVC SN4 D110 (esgoto) | C89: ESG | D89: m | I89: 22 | J89: =IF(AND(A89="",B89=""),"",IF(SUM(E89:H89)>0,SUM(E89:H89),I89)) -> 22 | K89: =IF(J89="","",ROUND(IF(SUM(E89:H89)>0,E89*(1+Config!$C$4)+F89*(1+Config!$C$5)+G89*(1+Config!$C$6)+H89*(1+Config!$C$7),I89*(1+Config!$C$8)),2)) -> 22.44 | M89: =IF(J89="","",IF(L89="",Config!$C$3,L89)) -> 0.2 | N89: =IF(K89="","",ROUND(K89*(1+M89),2)) -> 26.93 | O89: Referência de mercado Porto/Aveiro (BASE_PRECOS_2026) | Q89: Jun-2026 | R89: C | S89: =IF(A89="","",COUNTIF(Registo!$B$2:$B$501,A89)) -> 0 | T89: =IF(OR(A89="",S89=0),"",LOOKUP(2,1/(Registo!$B$2:$B$501=A89),Registo!$E$2:$E$501)) | U89: Código mantido da base 2026; especialidade reclassificada
A90: HID.06 | B90: Ramal de descarga PVC D50 (esgoto) | C90: ESG | D90: m | I90: 14 | J90: =IF(AND(A90="",B90=""),"",IF(SUM(E90:H90)>0,SUM(E90:H90),I90)) -> 14 | K90: =IF(J90="","",ROUND(IF(SUM(E90:H90)>0,E90*(1+Config!$C$4)+F90*(1+Config!$C$5)+G90*(1+Config!$C$6)+H90*(1+Config!$C$7),I90*(1+Config!$C$8)),2)) -> 14.28 | M90: =IF(J90="","",IF(L90="",Config!$C$3,L90)) -> 0.2 | N90: =IF(K90="","",ROUND(K90*(1+M90),2)) -> 17.14 | O90: Referência de mercado Porto/Aveiro (BASE_PRECOS_2026) | Q90: Jun-2026 | R90: C | S90: =IF(A90="","",COUNTIF(Registo!$B$2:$B$501,A90)) -> 0 | T90: =IF(OR(A90="",S90=0),"",LOOKUP(2,1/(Registo!$B$2:$B$501=A90),Registo!$E$2:$E$501)) | U90: Código mantido da base 2026; especialidade reclassificada
A91: HID.07 | B91: Ramal de descarga PVC D75 | C91: ESG | D91: m | I91: 18 | J91: =IF(AND(A91="",B91=""),"",IF(SUM(E91:H91)>0,SUM(E91:H91),I91)) -> 18 | K91: =IF(J91="","",ROUND(IF(SUM(E91:H91)>0,E91*(1+Config!$C$4)+F91*(1+Config!$C$5)+G91*(1+Config!$C$6)+H91*(1+Config!$C$7),I91*(1+Config!$C$8)),2)) -> 18.36 | M91: =IF(J91="","",IF(L91="",Config!$C$3,L91)) -> 0.2 | N91: =IF(K91="","",ROUND(K91*(1+M91),2)) -> 22.03 | O91: Referência de mercado Porto/Aveiro (BASE_PRECOS_2026) | Q91: Jun-2026 | R91: C | S91: =IF(A91="","",COUNTIF(Registo!$B$2:$B$501,A91)) -> 0 | T91: =IF(OR(A91="",S91=0),"",LOOKUP(2,1/(Registo!$B$2:$B$501=A91),Registo!$E$2:$E$501)) | U91: Código mantido da base 2026; especialidade reclassificada
A92: HID.08 | B92: Caixa de visita betão D60 (h até 1,2m) | C92: ESG | D92: un | I92: 320 | J92: =IF(AND(A92="",B92=""),"",IF(SUM(E92:H92)>0,SUM(E92:H92),I92)) -> 320 | K92: =IF(J92="","",ROUND(IF(SUM(E92:H92)>0,E92*(1+Config!$C$4)+F92*(1+Config!$C$5)+G92*(1+Config!$C$6)+H92*(1+Config!$C$7),I92*(1+Config!$C$8)),2)) -> 326.4 | M92: =IF(J92="","",IF(L92="",Config!$C$3,L92)) -> 0.2 | N92: =IF(K92="","",ROUND(K92*(1+M92),2)) -> 391.68 | O92: Referência de mercado Porto/Aveiro (BASE_PRECOS_2026) | Q92: Jun-2026 | R92: C | S92: =IF(A92="","",COUNTIF(Registo!$B$2:$B$501,A92)) -> 0 | T92: =IF(OR(A92="",S92=0),"",LOOKUP(2,1/(Registo!$B$2:$B$501=A92),Registo!$E$2:$E$501)) | U92: Código mantido da base 2026; especialidade reclassificada
A93: ELE.01 | B93: Ramal eléctrico monofásico (Caixa Contador) | C93: ELE | D93: un | I93: 850 | J93: =IF(AND(A93="",B93=""),"",IF(SUM(E93:H93)>0,SUM(E93:H93),I93)) -> 850 | K93: =IF(J93="","",ROUND(IF(SUM(E93:H93)>0,E93*(1+Config!$C$4)+F93*(1+Config!$C$5)+G93*(1+Config!$C$6)+H93*(1+Config!$C$7),I93*(1+Config!$C$8)),2)) -> 867 | M93: =IF(J93="","",IF(L93="",Config!$C$3,L93)) -> 0.2 | N93: =IF(K93="","",ROUND(K93*(1+M93),2)) -> 1040.4 | O93: Referência de mercado Porto/Aveiro (BASE_PRECOS_2026) | Q93: Jun-2026 | R93: C | S93: =IF(A93="","",COUNTIF(Registo!$B$2:$B$501,A93)) -> 0 | T93: =IF(OR(A93="",S93=0),"",LOOKUP(2,1/(Registo!$B$2:$B$501=A93),Registo!$E$2:$E$501))
A94: ELE.02 | B94: Quadro eléctrico geral até 16 disjuntores | C94: ELE | D94: un | I94: 680 | J94: =IF(AND(A94="",B94=""),"",IF(SUM(E94:H94)>0,SUM(E94:H94),I94)) -> 680 | K94: =IF(J94="","",ROUND(IF(SUM(E94:H94)>0,E94*(1+Config!$C$4)+F94*(1+Config!$C$5)+G94*(1+Config!$C$6)+H94*(1+Config!$C$7),I94*(1+Config!$C$8)),2)) -> 693.6 | M94: =IF(J94="","",IF(L94="",Config!$C$3,L94)) -> 0.2 | N94: =IF(K94="","",ROUND(K94*(1+M94),2)) -> 832.32 | O94: Referência de mercado Porto/Aveiro (BASE_PRECOS_2026) | Q94: Jun-2026 | R94: C | S94: =IF(A94="","",COUNTIF(Registo!$B$2:$B$501,A94)) -> 0 | T94: =IF(OR(A94="",S94=0),"",LOOKUP(2,1/(Registo!$B$2:$B$501=A94),Registo!$E$2:$E$501))
A95: ELE.03 | B95: Quadro eléctrico geral até 24 disjuntores | C95: ELE | D95: un | I95: 920 | J95: =IF(AND(A95="",B95=""),"",IF(SUM(E95:H95)>0,SUM(E95:H95),I95)) -> 920 | K95: =IF(J95="","",ROUND(IF(SUM(E95:H95)>0,E95*(1+Config!$C$4)+F95*(1+Config!$C$5)+G95*(1+Config!$C$6)+H95*(1+Config!$C$7),I95*(1+Config!$C$8)),2)) -> 938.4 | M95: =IF(J95="","",IF(L95="",Config!$C$3,L95)) -> 0.2 | N95: =IF(K95="","",ROUND(K95*(1+M95),2)) -> 1126.08 | O95: Referência de mercado Porto/Aveiro (BASE_PRECOS_2026) | Q95: Jun-2026 | R95: C | S95: =IF(A95="","",COUNTIF(Registo!$B$2:$B$501,A95)) -> 0 | T95: =IF(OR(A95="",S95=0),"",LOOKUP(2,1/(Registo!$B$2:$B$501=A95),Registo!$E$2:$E$501))
A96: ELE.04 | B96: Circuito iluminação (cabo + canalização) | C96: ELE | D96: m | I96: 8.5 | J96: =IF(AND(A96="",B96=""),"",IF(SUM(E96:H96)>0,SUM(E96:H96),I96)) -> 8.5 | K96: =IF(J96="","",ROUND(IF(SUM(E96:H96)>0,E96*(1+Config!$C$4)+F96*(1+Config!$C$5)+G96*(1+Config!$C$6)+H96*(1+Config!$C$7),I96*(1+Config!$C$8)),2)) -> 8.67 | M96: =IF(J96="","",IF(L96="",Config!$C$3,L96)) -> 0.2 | N96: =IF(K96="","",ROUND(K96*(1+M96),2)) -> 10.4 | O96: Referência de mercado Porto/Aveiro (BASE_PRECOS_2026) | Q96: Jun-2026 | R96: C | S96: =IF(A96="","",COUNTIF(Registo!$B$2:$B$501,A96)) -> 0 | T96: =IF(OR(A96="",S96=0),"",LOOKUP(2,1/(Registo!$B$2:$B$501=A96),Registo!$E$2:$E$501))
A97: ELE.05 | B97: Circuito tomadas (cabo + canalização) | C97: ELE | D97: m | I97: 9.5 | J97: =IF(AND(A97="",B97=""),"",IF(SUM(E97:H97)>0,SUM(E97:H97),I97)) -> 9.5 | K97: =IF(J97="","",ROUND(IF(SUM(E97:H97)>0,E97*(1+Config!$C$4)+F97*(1+Config!$C$5)+G97*(1+Config!$C$6)+H97*(1+Config!$C$7),I97*(1+Config!$C$8)),2)) -> 9.69 | M97: =IF(J97="","",IF(L97="",Config!$C$3,L97)) -> 0.2 | N97: =IF(K97="","",ROUND(K97*(1+M97),2)) -> 11.63 | O97: Referência de mercado Porto/Aveiro (BASE_PRECOS_2026) | Q97: Jun-2026 | R97: C | S97: =IF(A97="","",COUNTIF(Registo!$B$2:$B$501,A97)) -> 0 | T97: =IF(OR(A97="",S97=0),"",LOOKUP(2,1/(Registo!$B$2:$B$501=A97),Registo!$E$2:$E$501))
A98: ELE.06 | B98: Ponto de luz (caixa + ligações) | C98: ELE | D98: un | I98: 45 | J98: =IF(AND(A98="",B98=""),"",IF(SUM(E98:H98)>0,SUM(E98:H98),I98)) -> 45 | K98: =IF(J98="","",ROUND(IF(SUM(E98:H98)>0,E98*(1+Config!$C$4)+F98*(1+Config!$C$5)+G98*(1+Config!$C$6)+H98*(1+Config!$C$7),I98*(1+Config!$C$8)),2)) -> 45.9 | M98: =IF(J98="","",IF(L98="",Config!$C$3,L98)) -> 0.2 | N98: =IF(K98="","",ROUND(K98*(1+M98),2)) -> 55.08 | O98: Referência de mercado Porto/Aveiro (BASE_PRECOS_2026) | Q98: Jun-2026 | R98: C | S98: =IF(A98="","",COUNTIF(Registo!$B$2:$B$501,A98)) -> 0 | T98: =IF(OR(A98="",S98=0),"",LOOKUP(2,1/(Registo!$B$2:$B$501=A98),Registo!$E$2:$E$501))
A99: ELE.07 | B99: Tomada dupla encastrada | C99: ELE | D99: un | I99: 35 | J99: =IF(AND(A99="",B99=""),"",IF(SUM(E99:H99)>0,SUM(E99:H99),I99)) -> 35 | K99: =IF(J99="","",ROUND(IF(SUM(E99:H99)>0,E99*(1+Config!$C$4)+F99*(1+Config!$C$5)+G99*(1+Config!$C$6)+H99*(1+Config!$C$7),I99*(1+Config!$C$8)),2)) -> 35.7 | M99: =IF(J99="","",IF(L99="",Config!$C$3,L99)) -> 0.2 | N99: =IF(K99="","",ROUND(K99*(1+M99),2)) -> 42.84 | O99: Referência de mercado Porto/Aveiro (BASE_PRECOS_2026) | Q99: Jun-2026 | R99: C | S99: =IF(A99="","",COUNTIF(Registo!$B$2:$B$501,A99)) -> 0 | T99: =IF(OR(A99="",S99=0),"",LOOKUP(2,1/(Registo!$B$2:$B$501=A99),Registo!$E$2:$E$501))
A100: ELE.08 | B100: Tomada 16A (forno/máquina) | C100: ELE | D100: un | I100: 45 | J100: =IF(AND(A100="",B100=""),"",IF(SUM(E100:H100)>0,SUM(E100:H100),I100)) -> 45 | K100: =IF(J100="","",ROUND(IF(SUM(E100:H100)>0,E100*(1+Config!$C$4)+F100*(1+Config!$C$5)+G100*(1+Config!$C$6)+H100*(1+Config!$C$7),I100*(1+Config!$C$8)),2)) -> 45.9 | M100: =IF(J100="","",IF(L100="",Config!$C$3,L100)) -> 0.2 | N100: =IF(K100="","",ROUND(K100*(1+M100),2)) -> 55.08 | O100: Referência de mercado Porto/Aveiro (BASE_PRECOS_2026) | Q100: Jun-2026 | R100: C | S100: =IF(A100="","",COUNTIF(Registo!$B$2:$B$501,A100)) -> 0 | T100: =IF(OR(A100="",S100=0),"",LOOKUP(2,1/(Registo!$B$2:$B$501=A100),Registo!$E$2:$E$501))
A101: ELE.09 | B101: Interruptor simples | C101: ELE | D101: un | I101: 28 | J101: =IF(AND(A101="",B101=""),"",IF(SUM(E101:H101)>0,SUM(E101:H101),I101)) -> 28 | K101: =IF(J101="","",ROUND(IF(SUM(E101:H101)>0,E101*(1+Config!$C$4)+F101*(1+Config!$C$5)+G101*(1+Config!$C$6)+H101*(1+Config!$C$7),I101*(1+Config!$C$8)),2)) -> 28.56 | M101: =IF(J101="","",IF(L101="",Config!$C$3,L101)) -> 0.2 | N101: =IF(K101="","",ROUND(K101*(1+M101),2)) -> 34.27 | O101: Referência de mercado Porto/Aveiro (BASE_PRECOS_2026) | Q101: Jun-2026 | R101: C | S101: =IF(A101="","",COUNTIF(Registo!$B$2:$B$501,A101)) -> 0 | T101: =IF(OR(A101="",S101=0),"",LOOKUP(2,1/(Registo!$B$2:$B$501=A101),Registo!$E$2:$E$501))
A102: ELE.10 | B102: Interruptor duplo | C102: ELE | D102: un | I102: 35 | J102: =IF(AND(A102="",B102=""),"",IF(SUM(E102:H102)>0,SUM(E102:H102),I102)) -> 35 | K102: =IF(J102="","",ROUND(IF(SUM(E102:H102)>0,E102*(1+Config!$C$4)+F102*(1+Config!$C$5)+G102*(1+Config!$C$6)+H102*(1+Config!$C$7),I102*(1+Config!$C$8)),2)) -> 35.7 | M102: =IF(J102="","",IF(L102="",Config!$C$3,L102)) -> 0.2 | N102: =IF(K102="","",ROUND(K102*(1+M102),2)) -> 42.84 | O102: Referência de mercado Porto/Aveiro (BASE_PRECOS_2026) | Q102: Jun-2026 | R102: C | S102: =IF(A102="","",COUNTIF(Registo!$B$2:$B$501,A102)) -> 0 | T102: =IF(OR(A102="",S102=0),"",LOOKUP(2,1/(Registo!$B$2:$B$501=A102),Registo!$E$2:$E$501))
A103: ELE.11 | B103: Campainha + botão | C103: ELE | D103: un | I103: 120 | J103: =IF(AND(A103="",B103=""),"",IF(SUM(E103:H103)>0,SUM(E103:H103),I103)) -> 120 | K103: =IF(J103="","",ROUND(IF(SUM(E103:H103)>0,E103*(1+Config!$C$4)+F103*(1+Config!$C$5)+G103*(1+Config!$C$6)+H103*(1+Config!$C$7),I103*(1+Config!$C$8)),2)) -> 122.4 | M103: =IF(J103="","",IF(L103="",Config!$C$3,L103)) -> 0.2 | N103: =IF(K103="","",ROUND(K103*(1+M103),2)) -> 146.88 | O103: Referência de mercado Porto/Aveiro (BASE_PRECOS_2026) | Q103: Jun-2026 | R103: C | S103: =IF(A103="","",COUNTIF(Registo!$B$2:$B$501,A103)) -> 0 | T103: =IF(OR(A103="",S103=0),"",LOOKUP(2,1/(Registo!$B$2:$B$501=A103),Registo!$E$2:$E$501))
A104: ELE.12 | B104: Videoporteiro básico | C104: ELE | D104: un | I104: 380 | J104: =IF(AND(A104="",B104=""),"",IF(SUM(E104:H104)>0,SUM(E104:H104),I104)) -> 380 | K104: =IF(J104="","",ROUND(IF(SUM(E104:H104)>0,E104*(1+Config!$C$4)+F104*(1+Config!$C$5)+G104*(1+Config!$C$6)+H104*(1+Config!$C$7),I104*(1+Config!$C$8)),2)) -> 387.6 | M104: =IF(J104="","",IF(L104="",Config!$C$3,L104)) -> 0.2 | N104: =IF(K104="","",ROUND(K104*(1+M104),2)) -> 465.12 | O104: Referência de mercado Porto/Aveiro (BASE_PRECOS_2026) | Q104: Jun-2026 | R104: C | S104: =IF(A104="","",COUNTIF(Registo!$B$2:$B$501,A104)) -> 0 | T104: =IF(OR(A104="",S104=0),"",LOOKUP(2,1/(Registo!$B$2:$B$501=A104),Registo!$E$2:$E$501))
... A107: ELE.15 | B107: Carregador EV monofásico 7,4kW | C107: ELE | D107: un | I107: 1200 | J107: =IF(AND(A107="",B107=""),"",IF(SUM(E107:H107)>0,SUM(E107:H107),I107)) -> 1200 | K107: =IF(J107="","",ROUND(IF(SUM(E107:H107)>0,E107*(1+Config!$C$4)+F107*(1+Config!$C$5)+G107*(1+Config!$C$6)+H107*(1+Config!$C$7),I107*(1+Config!$C$8)),2)) -> 1224 | M107: =IF(J107="","",IF(L107="",Config!$C$3,L107)) -> 0.2 | N107: =IF(K107="","",ROUND(K107*(1+M107),2)) -> 1468.8 | O107: Referência de mercado Porto/Aveiro (BASE_PRECOS_2026) | Q107: Jun-2026 | R107: C | S107: =IF(A107="","",COUNTIF(Registo!$B$2:$B$501,A107)) -> 0 | T107: =IF(OR(A107="",S107=0),"",LOOKUP(2,1/(Registo!$B$2:$B$501=A107),Registo!$E$2:$E$501))
A108: ELE.16 | B108: Instalação elétrica embebida (apartamento), tubagem VD, caixas, cablagem e aparelhagem | C108: ELE | D108: vg | I108: 3400 | J108: =IF(AND(A108="",B108=""),"",IF(SUM(E108:H108)>0,SUM(E108:H108),I108)) -> 3400 | K108: =IF(J108="","",ROUND(IF(SUM(E108:H108)>0,E108*(1+Config!$C$4)+F108*(1+Config!$C$5)+G108*(1+Config!$C$6)+H108*(1+Config!$C$7),I108*(1+Config!$C$8)),2)) -> 3468 | M108: =IF(J108="","",IF(L108="",Config!$C$3,L108)) -> 0.2 | N108: =IF(K108="","",ROUND(K108*(1+M108),2)) -> 4161.6 | O108: Orçamento próprio (custo, antes de margem) | P108: Ribeira – remodelação (L99) | Q108: 2026 | R108: B | S108: =IF(A108="","",COUNTIF(Registo!$B$2:$B$501,A108)) -> 0 | T108: =IF(OR(A108="",S108=0),"",LOOKUP(2,1/(Registo!$B$2:$B$501=A108),Registo!$E$2:$E$501)) | U108: Inclui agravamento por acesso condicionado (transporte manual 100 m + escadaria, 1.º andar s/ elevador)
A109: ELE.17 | B109: Aparelhagem elétrica (tipo EFAPEL), cor branca, fornecimento e instalação | C109: ELE | D109: un | I109: 32 | J109: =IF(AND(A109="",B109=""),"",IF(SUM(E109:H109)>0,SUM(E109:H109),I109)) -> 32 | K109: =IF(J109="","",ROUND(IF(SUM(E109:H109)>0,E109*(1+Config!$C$4)+F109*(1+Config!$C$5)+G109*(1+Config!$C$6)+H109*(1+Config!$C$7),I109*(1+Config!$C$8)),2)) -> 32.64 | M109: =IF(J109="","",IF(L109="",Config!$C$3,L109)) -> 0.2 | N109: =IF(K109="","",ROUND(K109*(1+M109),2)) -> 39.17 | O109: Orçamento próprio (custo, antes de margem) | P109: Ribeira – remodelação (L99) | Q109: 2026 | R109: B | S109: =IF(A109="","",COUNTIF(Registo!$B$2:$B$501,A109)) -> 0 | T109: =IF(OR(A109="",S109=0),"",LOOKUP(2,1/(Registo!$B$2:$B$501=A109),Registo!$E$2:$E$501)) | U109: Inclui agravamento por acesso condicionado (transporte manual 100 m + escadaria, 1.º andar s/ elevador)
A110: ELE.18 | B110: Iluminação LED encastrada em teto falso | C110: ELE | D110: un | I110: 44 | J110: =IF(AND(A110="",B110=""),"",IF(SUM(E110:H110)>0,SUM(E110:H110),I110)) -> 44 | K110: =IF(J110="","",ROUND(IF(SUM(E110:H110)>0,E110*(1+Config!$C$4)+F110*(1+Config!$C$5)+G110*(1+Config!$C$6)+H110*(1+Config!$C$7),I110*(1+Config!$C$8)),2)) -> 44.88 | M110: =IF(J110="","",IF(L110="",Config!$C$3,L110)) -> 0.2 | N110: =IF(K110="","",ROUND(K110*(1+M110),2)) -> 53.86 | O110: Orçamento próprio (custo, antes de margem) | P110: Ribeira – remodelação (L99) | Q110: 2026 | R110: B | S110: =IF(A110="","",COUNTIF(Registo!$B$2:$B$501,A110)) -> 0 | T110: =IF(OR(A110="",S110=0),"",LOOKUP(2,1/(Registo!$B$2:$B$501=A110),Registo!$E$2:$E$501)) | U110: Inclui agravamento por acesso condicionado (transporte manual 100 m + escadaria, 1.º andar s/ elevador)
A111: ELE.19 | B111: Circuito dedicado para instalações sanitárias e equipamentos | C111: ELE | D111: vg | I111: 420 | J111: =IF(AND(A111="",B111=""),"",IF(SUM(E111:H111)>0,SUM(E111:H111),I111)) -> 420 | K111: =IF(J111="","",ROUND(IF(SUM(E111:H111)>0,E111*(1+Config!$C$4)+F111*(1+Config!$C$5)+G111*(1+Config!$C$6)+H111*(1+Config!$C$7),I111*(1+Config!$C$8)),2)) -> 428.4 | M111: =IF(J111="","",IF(L111="",Config!$C$3,L111)) -> 0.2 | N111: =IF(K111="","",ROUND(K111*(1+M111),2)) -> 514.08 | O111: Orçamento próprio (custo, antes de margem) | P111: Ribeira – remodelação (L99) | Q111: 2026 | R111: B | S111: =IF(A111="","",COUNTIF(Registo!$B$2:$B$501,A111)) -> 0 | T111: =IF(OR(A111="",S111=0),"",LOOKUP(2,1/(Registo!$B$2:$B$501=A111),Registo!$E$2:$E$501)) | U111: Inclui agravamento por acesso condicionado (transporte manual 100 m + escadaria, 1.º andar s/ elevador)
A112: ELE.20 | B112: Revisão e adaptação de quadro elétrico existente (diferencial e disjuntores) | C112: ELE | D112: vg | I112: 500 | J112: =IF(AND(A112="",B112=""),"",IF(SUM(E112:H112)>0,SUM(E112:H112),I112)) -> 500 | K112: =IF(J112="","",ROUND(IF(SUM(E112:H112)>0,E112*(1+Config!$C$4)+F112*(1+Config!$C$5)+G112*(1+Config!$C$6)+H112*(1+Config!$C$7),I112*(1+Config!$C$8)),2)) -> 510 | M112: =IF(J112="","",IF(L112="",Config!$C$3,L112)) -> 0.2 | N112: =IF(K112="","",ROUND(K112*(1+M112),2)) -> 612 | O112: Orçamento próprio (custo, antes de margem) | P112: Ribeira – remodelação (L99) | Q112: 2026 | R112: B | S112: =IF(A112="","",COUNTIF(Registo!$B$2:$B$501,A112)) -> 0 | T112: =IF(OR(A112="",S112=0),"",LOOKUP(2,1/(Registo!$B$2:$B$501=A112),Registo!$E$2:$E$501)) | U112: Inclui agravamento por acesso condicionado (transporte manual 100 m + escadaria, 1.º andar s/ elevador)
A113: ITE.01 | B113: Passagem de caixilharia ITED (caixa + calha) | C113: ITED | D113: un | I113: 85 | J113: =IF(AND(A113="",B113=""),"",IF(SUM(E113:H113)>0,SUM(E113:H113),I113)) -> 85 | K113: =IF(J113="","",ROUND(IF(SUM(E113:H113)>0,E113*(1+Config!$C$4)+F113*(1+Config!$C$5)+G113*(1+Config!$C$6)+H113*(1+Config!$C$7),I113*(1+Config!$C$8)),2)) -> 86.7 | M113: =IF(J113="","",IF(L113="",Config!$C$3,L113)) -> 0.2 | N113: =IF(K113="","",ROUND(K113*(1+M113),2)) -> 104.04 | O113: Referência de mercado Porto/Aveiro (BASE_PRECOS_2026) | Q113: Jun-2026 | R113: C | S113: =IF(A113="","",COUNTIF(Registo!$B$2:$B$501,A113)) -> 0 | T113: =IF(OR(A113="",S113=0),"",LOOKUP(2,1/(Registo!$B$2:$B$501=A113),Registo!$E$2:$E$501))
A114: ITE.02 | B114: Tomada TV+TEL+DADOS RJ45 | C114: ITED | D114: un | I114: 45 | J114: =IF(AND(A114="",B114=""),"",IF(SUM(E114:H114)>0,SUM(E114:H114),I114)) -> 45 | K114: =IF(J114="","",ROUND(IF(SUM(E114:H114)>0,E114*(1+Config!$C$4)+F114*(1+Config!$C$5)+G114*(1+Config!$C$6)+H114*(1+Config!$C$7),I114*(1+Config!$C$8)),2)) -> 45.9 | M114: =IF(J114="","",IF(L114="",Config!$C$3,L114)) -> 0.2 | N114: =IF(K114="","",ROUND(K114*(1+M114),2)) -> 55.08 | O114: Referência de mercado Porto/Aveiro (BASE_PRECOS_2026) | Q114: Jun-2026 | R114: C | S114: =IF(A114="","",COUNTIF(Registo!$B$2:$B$501,A114)) -> 0 | T114: =IF(OR(A114="",S114=0),"",LOOKUP(2,1/(Registo!$B$2:$B$501=A114),Registo!$E$2:$E$501))
A115: ITE.03 | B115: Caixa ITED individual (ATI) | C115: ITED | D115: un | I115: 320 | J115: =IF(AND(A115="",B115=""),"",IF(SUM(E115:H115)>0,SUM(E115:H115),I115)) -> 320 | K115: =IF(J115="","",ROUND(IF(SUM(E115:H115)>0,E115*(1+Config!$C$4)+F115*(1+Config!$C$5)+G115*(1+Config!$C$6)+H115*(1+Config!$C$7),I115*(1+Config!$C$8)),2)) -> 326.4 | M115: =IF(J115="","",IF(L115="",Config!$C$3,L115)) -> 0.2 | N115: =IF(K115="","",ROUND(K115*(1+M115),2)) -> 391.68 | O115: Referência de mercado Porto/Aveiro (BASE_PRECOS_2026) | Q115: Jun-2026 | R115: C | S115: =IF(A115="","",COUNTIF(Registo!$B$2:$B$501,A115)) -> 0 | T115: =IF(OR(A115="",S115=0),"",LOOKUP(2,1/(Registo!$B$2:$B$501=A115),Registo!$E$2:$E$501))
A116: ITE.04 | B116: Caixa ITED colectiva (ATE) | C116: ITED | D116: un | I116: 580 | J116: =IF(AND(A116="",B116=""),"",IF(SUM(E116:H116)>0,SUM(E116:H116),I116)) -> 580 | K116: =IF(J116="","",ROUND(IF(SUM(E116:H116)>0,E116*(1+Config!$C$4)+F116*(1+Config!$C$5)+G116*(1+Config!$C$6)+H116*(1+Config!$C$7),I116*(1+Config!$C$8)),2)) -> 591.6 | M116: =IF(J116="","",IF(L116="",Config!$C$3,L116)) -> 0.2 | N116: =IF(K116="","",ROUND(K116*(1+M116),2)) -> 709.92 | O116: Referência de mercado Porto/Aveiro (BASE_PRECOS_2026) | Q116: Jun-2026 | R116: C | S116: =IF(A116="","",COUNTIF(Registo!$B$2:$B$501,A116)) -> 0 | T116: =IF(OR(A116="",S116=0),"",LOOKUP(2,1/(Registo!$B$2:$B$501=A116),Registo!$E$2:$E$501))
A117: ITE.05 | B117: Cabo coaxial RG6 (instalação) | C117: ITED | D117: m | I117: 4.5 | J117: =IF(AND(A117="",B117=""),"",IF(SUM(E117:H117)>0,SUM(E117:H117),I117)) -> 4.5 | K117: =IF(J117="","",ROUND(IF(SUM(E117:H117)>0,E117*(1+Config!$C$4)+F117*(1+Config!$C$5)+G117*(1+Config!$C$6)+H117*(1+Config!$C$7),I117*(1+Config!$C$8)),2)) -> 4.59 | M117: =IF(J117="","",IF(L117="",Config!$C$3,L117)) -> 0.2 | N117: =IF(K117="","",ROUND(K117*(1+M117),2)) -> 5.51 | O117: Referência de mercado Porto/Aveiro (BASE_PRECOS_2026) | Q117: Jun-2026 | R117: C | S117: =IF(A117="","",COUNTIF(Registo!$B$2:$B$501,A117)) -> 0 | T117: =IF(OR(A117="",S117=0),"",LOOKUP(2,1/(Registo!$B$2:$B$501=A117),Registo!$E$2:$E$501))
A118: ITE.06 | B118: Router/switch instalação e config. | C118: ITED | D118: un | I118: 180 | J118: =IF(AND(A118="",B118=""),"",IF(SUM(E118:H118)>0,SUM(E118:H118),I118)) -> 180 | K118: =IF(J118="","",ROUND(IF(SUM(E118:H118)>0,E118*(1+Config!$C$4)+F118*(1+Config!$C$5)+G118*(1+Config!$C$6)+H118*(1+Config!$C$7),I118*(1+Config!$C$8)),2)) -> 183.6 | M118: =IF(J118="","",IF(L118="",Config!$C$3,L118)) -> 0.2 | N118: =IF(K118="","",ROUND(K118*(1+M118),2)) -> 220.32 | O118: Referência de mercado Porto/Aveiro (BASE_PRECOS_2026) | Q118: Jun-2026 | R118: C | S118: =IF(A118="","",COUNTIF(Registo!$B$2:$B$501,A118)) -> 0 | T118: =IF(OR(A118="",S118=0),"",LOOKUP(2,1/(Registo!$B$2:$B$501=A118),Registo!$E$2:$E$501))
A119: AVA.01 | B119: Split 9000 BTU (A+++) fornecimento + install. | C119: AVAC | D119: un | I119: 1200 | J119: =IF(AND(A119="",B119=""),"",IF(SUM(E119:H119)>0,SUM(E119:H119),I119)) -> 1200 | K119: =IF(J119="","",ROUND(IF(SUM(E119:H119)>0,E119*(1+Config!$C$4)+F119*(1+Config!$C$5)+G119*(1+Config!$C$6)+H119*(1+Config!$C$7),I119*(1+Config!$C$8)),2)) -> 1224 | M119: =IF(J119="","",IF(L119="",Config!$C$3,L119)) -> 0.2 | N119: =IF(K119="","",ROUND(K119*(1+M119),2)) -> 1468.8 | O119: Referência de mercado Porto/Aveiro (BASE_PRECOS_2026) | Q119: Jun-2026 | R119: C | S119: =IF(A119="","",COUNTIF(Registo!$B$2:$B$501,A119)) -> 0 | T119: =IF(OR(A119="",S119=0),"",LOOKUP(2,1/(Registo!$B$2:$B$501=A119),Registo!$E$2:$E$501))
A120: AVA.02 | B120: Split 12000 BTU (A+++) | C120: AVAC | D120: un | I120: 1450 | J120: =IF(AND(A120="",B120=""),"",IF(SUM(E120:H120)>0,SUM(E120:H120),I120)) -> 1450 | K120: =IF(J120="","",ROUND(IF(SUM(E120:H120)>0,E120*(1+Config!$C$4)+F120*(1+Config!$C$5)+G120*(1+Config!$C$6)+H120*(1+Config!$C$7),I120*(1+Config!$C$8)),2)) -> 1479 | M120: =IF(J120="","",IF(L120="",Config!$C$3,L120)) -> 0.2 | N120: =IF(K120="","",ROUND(K120*(1+M120),2)) -> 1774.8 | O120: Referência de mercado Porto/Aveiro (BASE_PRECOS_2026) | Q120: Jun-2026 | R120: C | S120: =IF(A120="","",COUNTIF(Registo!$B$2:$B$501,A120)) -> 0 | T120: =IF(OR(A120="",S120=0),"",LOOKUP(2,1/(Registo!$B$2:$B$501=A120),Registo!$E$2:$E$501))
A121: AVA.03 | B121: Split 18000 BTU (A+++) | C121: AVAC | D121: un | I121: 1850 | J121: =IF(AND(A121="",B121=""),"",IF(SUM(E121:H121)>0,SUM(E121:H121),I121)) -> 1850 | K121: =IF(J121="","",ROUND(IF(SUM(E121:H121)>0,E121*(1+Config!$C$4)+F121*(1+Config!$C$5)+G121*(1+Config!$C$6)+H121*(1+Config!$C$7),I121*(1+Config!$C$8)),2)) -> 1887 | M121: =IF(J121="","",IF(L121="",Config!$C$3,L121)) -> 0.2 | N121: =IF(K121="","",ROUND(K121*(1+M121),2)) -> 2264.4 | O121: Referência de mercado Porto/Aveiro (BASE_PRECOS_2026) | Q121: Jun-2026 | R121: C | S121: =IF(A121="","",COUNTIF(Registo!$B$2:$B$501,A121)) -> 0 | T121: =IF(OR(A121="",S121=0),"",LOOKUP(2,1/(Registo!$B$2:$B$501=A121),Registo!$E$2:$E$501))
A122: AVA.04 | B122: Multi-split 3×9000 BTU | C122: AVAC | D122: un | I122: 3200 | J122: =IF(AND(A122="",B122=""),"",IF(SUM(E122:H122)>0,SUM(E122:H122),I122)) -> 3200 | K122: =IF(J122="","",ROUND(IF(SUM(E122:H122)>0,E122*(1+Config!$C$4)+F122*(1+Config!$C$5)+G122*(1+Config!$C$6)+H122*(1+Config!$C$7),I122*(1+Config!$C$8)),2)) -> 3264 | M122: =IF(J122="","",IF(L122="",Config!$C$3,L122)) -> 0.2 | N122: =IF(K122="","",ROUND(K122*(1+M122),2)) -> 3916.8 | O122: Referência de mercado Porto/Aveiro (BASE_PRECOS_2026) | Q122: Jun-2026 | R122: C | S122: =IF(A122="","",COUNTIF(Registo!$B$2:$B$501,A122)) -> 0 | T122: =IF(OR(A122="",S122=0),"",LOOKUP(2,1/(Registo!$B$2:$B$501=A122),Registo!$E$2:$E$501))
A123: AVA.05 | B123: VRF sistema comercial (por kW frio) | C123: AVAC | D123: kW | I123: 480 | J123: =IF(AND(A123="",B123=""),"",IF(SUM(E123:H123)>0,SUM(E123:H123),I123)) -> 480 | K123: =IF(J123="","",ROUND(IF(SUM(E123:H123)>0,E123*(1+Config!$C$4)+F123*(1+Config!$C$5)+G123*(1+Config!$C$6)+H123*(1+Config!$C$7),I123*(1+Config!$C$8)),2)) -> 489.6 | M123: =IF(J123="","",IF(L123="",Config!$C$3,L123)) -> 0.2 | N123: =IF(K123="","",ROUND(K123*(1+M123),2)) -> 587.52 | O123: Referência de mercado Porto/Aveiro (BASE_PRECOS_2026) | Q123: Jun-2026 | R123: C | S123: =IF(A123="","",COUNTIF(Registo!$B$2:$B$501,A123)) -> 0 | T123: =IF(OR(A123="",S123=0),"",LOOKUP(2,1/(Registo!$B$2:$B$501=A123),Registo!$E$2:$E$501))
A124: AVA.06 | B124: VMC simples fluxo (fornecimento + install.) | C124: AVAC | D124: un | I124: 950 | J124: =IF(AND(A124="",B124=""),"",IF(SUM(E124:H124)>0,SUM(E124:H124),I124)) -> 950 | K124: =IF(J124="","",ROUND(IF(SUM(E124:H124)>0,E124*(1+Config!$C$4)+F124*(1+Config!$C$5)+G124*(1+Config!$C$6)+H124*(1+Config!$C$7),I124*(1+Config!$C$8)),2)) -> 969 | M124: =IF(J124="","",IF(L124="",Config!$C$3,L124)) -> 0.2 | N124: =IF(K124="","",ROUND(K124*(1+M124),2)) -> 1162.8 | O124: Referência de mercado Porto/Aveiro (BASE_PRECOS_2026) | Q124: Jun-2026 | R124: C | S124: =IF(A124="","",COUNTIF(Registo!$B$2:$B$501,A124)) -> 0 | T124: =IF(OR(A124="",S124=0),"",LOOKUP(2,1/(Registo!$B$2:$B$501=A124),Registo!$E$2:$E$501))
... A142: TER.03 | B142: Isolamento MW 50mm em paredes (caixa-de-ar) | C142: TERM | D142: m² | I142: 12 | J142: =IF(AND(A142="",B142=""),"",IF(SUM(E142:H142)>0,SUM(E142:H142),I142)) -> 12 | K142: =IF(J142="","",ROUND(IF(SUM(E142:H142)>0,E142*(1+Config!$C$4)+F142*(1+Config!$C$5)+G142*(1+Config!$C$6)+H142*(1+Config!$C$7),I142*(1+Config!$C$8)),2)) -> 12.24 | M142: =IF(J142="","",IF(L142="",Config!$C$3,L142)) -> 0.2 | N142: =IF(K142="","",ROUND(K142*(1+M142),2)) -> 14.69 | O142: Referência de mercado Porto/Aveiro (BASE_PRECOS_2026) | Q142: Jun-2026 | R142: C | S142: =IF(A142="","",COUNTIF(Registo!$B$2:$B$501,A142)) -> 0 | T142: =IF(OR(A142="",S142=0),"",LOOKUP(2,1/(Registo!$B$2:$B$501=A142),Registo!$E$2:$E$501))
A143: TER.04 | B143: Isolamento acústico pavimento (betão celular 5cm) | C143: ACU | D143: m² | I143: 18 | J143: =IF(AND(A143="",B143=""),"",IF(SUM(E143:H143)>0,SUM(E143:H143),I143)) -> 18 | K143: =IF(J143="","",ROUND(IF(SUM(E143:H143)>0,E143*(1+Config!$C$4)+F143*(1+Config!$C$5)+G143*(1+Config!$C$6)+H143*(1+Config!$C$7),I143*(1+Config!$C$8)),2)) -> 18.36 | M143: =IF(J143="","",IF(L143="",Config!$C$3,L143)) -> 0.2 | N143: =IF(K143="","",ROUND(K143*(1+M143),2)) -> 22.03 | O143: Referência de mercado Porto/Aveiro (BASE_PRECOS_2026) | Q143: Jun-2026 | R143: C | S143: =IF(A143="","",COUNTIF(Registo!$B$2:$B$501,A143)) -> 0 | T143: =IF(OR(A143="",S143=0),"",LOOKUP(2,1/(Registo!$B$2:$B$501=A143),Registo!$E$2:$E$501)) | U143: Código mantido da base 2026; especialidade reclassificada
A144: TER.05 | B144: Isolamento acústico tecto falso (MW 40mm) | C144: ACU | D144: m² | I144: 15 | J144: =IF(AND(A144="",B144=""),"",IF(SUM(E144:H144)>0,SUM(E144:H144),I144)) -> 15 | K144: =IF(J144="","",ROUND(IF(SUM(E144:H144)>0,E144*(1+Config!$C$4)+F144*(1+Config!$C$5)+G144*(1+Config!$C$6)+H144*(1+Config!$C$7),I144*(1+Config!$C$8)),2)) -> 15.3 | M144: =IF(J144="","",IF(L144="",Config!$C$3,L144)) -> 0.2 | N144: =IF(K144="","",ROUND(K144*(1+M144),2)) -> 18.36 | O144: Referência de mercado Porto/Aveiro (BASE_PRECOS_2026) | Q144: Jun-2026 | R144: C | S144: =IF(A144="","",COUNTIF(Registo!$B$2:$B$501,A144)) -> 0 | T144: =IF(OR(A144="",S144=0),"",LOOKUP(2,1/(Registo!$B$2:$B$501=A144),Registo!$E$2:$E$501)) | U144: Código mantido da base 2026; especialidade reclassificada
A145: CAR.01 | B145: Roupeiro embutido MDF lacado (por metro linear) | C145: CARP | D145: m | I145: 850 | J145: =IF(AND(A145="",B145=""),"",IF(SUM(E145:H145)>0,SUM(E145:H145),I145)) -> 850 | K145: =IF(J145="","",ROUND(IF(SUM(E145:H145)>0,E145*(1+Config!$C$4)+F145*(1+Config!$C$5)+G145*(1+Config!$C$6)+H145*(1+Config!$C$7),I145*(1+Config!$C$8)),2)) -> 867 | M145: =IF(J145="","",IF(L145="",Config!$C$3,L145)) -> 0.2 | N145: =IF(K145="","",ROUND(K145*(1+M145),2)) -> 1040.4 | O145: Referência de mercado Porto/Aveiro (BASE_PRECOS_2026) | Q145: Jun-2026 | R145: C | S145: =IF(A145="","",COUNTIF(Registo!$B$2:$B$501,A145)) -> 0 | T145: =IF(OR(A145="",S145=0),"",LOOKUP(2,1/(Registo!$B$2:$B$501=A145),Registo!$E$2:$E$501))
A146: CAR.02 | B146: Cozinha MDF lacado (por metro linear) | C146: CARP | D146: m | I146: 1200 | J146: =IF(AND(A146="",B146=""),"",IF(SUM(E146:H146)>0,SUM(E146:H146),I146)) -> 1200 | K146: =IF(J146="","",ROUND(IF(SUM(E146:H146)>0,E146*(1+Config!$C$4)+F146*(1+Config!$C$5)+G146*(1+Config!$C$6)+H146*(1+Config!$C$7),I146*(1+Config!$C$8)),2)) -> 1224 | M146: =IF(J146="","",IF(L146="",Config!$C$3,L146)) -> 0.2 | N146: =IF(K146="","",ROUND(K146*(1+M146),2)) -> 1468.8 | O146: Referência de mercado Porto/Aveiro (BASE_PRECOS_2026) | Q146: Jun-2026 | R146: C | S146: =IF(A146="","",COUNTIF(Registo!$B$2:$B$501,A146)) -> 0 | T146: =IF(OR(A146="",S146=0),"",LOOKUP(2,1/(Registo!$B$2:$B$501=A146),Registo!$E$2:$E$501))
A147: CAR.03 | B147: Casa de banho em MDF lacado (móvel+lavatório) | C147: CARP | D147: un | I147: 680 | J147: =IF(AND(A147="",B147=""),"",IF(SUM(E147:H147)>0,SUM(E147:H147),I147)) -> 680 | K147: =IF(J147="","",ROUND(IF(SUM(E147:H147)>0,E147*(1+Config!$C$4)+F147*(1+Config!$C$5)+G147*(1+Config!$C$6)+H147*(1+Config!$C$7),I147*(1+Config!$C$8)),2)) -> 693.6 | M147: =IF(J147="","",IF(L147="",Config!$C$3,L147)) -> 0.2 | N147: =IF(K147="","",ROUND(K147*(1+M147),2)) -> 832.32 | O147: Referência de mercado Porto/Aveiro (BASE_PRECOS_2026) | Q147: Jun-2026 | R147: C | S147: =IF(A147="","",COUNTIF(Registo!$B$2:$B$501,A147)) -> 0 | T147: =IF(OR(A147="",S147=0),"",LOOKUP(2,1/(Registo!$B$2:$B$501=A147),Registo!$E$2:$E$501))
A148: CAR.04 | B148: Escada em madeira maciça (por degrau) | C148: CARP | D148: un | I148: 280 | J148: =IF(AND(A148="",B148=""),"",IF(SUM(E148:H148)>0,SUM(E148:H148),I148)) -> 280 | K148: =IF(J148="","",ROUND(IF(SUM(E148:H148)>0,E148*(1+Config!$C$4)+F148*(1+Config!$C$5)+G148*(1+Config!$C$6)+H148*(1+Config!$C$7),I148*(1+Config!$C$8)),2)) -> 285.6 | M148: =IF(J148="","",IF(L148="",Config!$C$3,L148)) -> 0.2 | N148: =IF(K148="","",ROUND(K148*(1+M148),2)) -> 342.72 | O148: Referência de mercado Porto/Aveiro (BASE_PRECOS_2026) | Q148: Jun-2026 | R148: C | S148: =IF(A148="","",COUNTIF(Registo!$B$2:$B$501,A148)) -> 0 | T148: =IF(OR(A148="",S148=0),"",LOOKUP(2,1/(Registo!$B$2:$B$501=A148),Registo!$E$2:$E$501))
A149: CAR.05 | B149: Soalho madeira maciça (colocação) | C149: CARP | D149: m² | I149: 45 | J149: =IF(AND(A149="",B149=""),"",IF(SUM(E149:H149)>0,SUM(E149:H149),I149)) -> 45 | K149: =IF(J149="","",ROUND(IF(SUM(E149:H149)>0,E149*(1+Config!$C$4)+F149*(1+Config!$C$5)+G149*(1+Config!$C$6)+H149*(1+Config!$C$7),I149*(1+Config!$C$8)),2)) -> 45.9 | M149: =IF(J149="","",IF(L149="",Config!$C$3,L149)) -> 0.2 | N149: =IF(K149="","",ROUND(K149*(1+M149),2)) -> 55.08 | O149: Referência de mercado Porto/Aveiro (BASE_PRECOS_2026) | Q149: Jun-2026 | R149: C | S149: =IF(A149="","",COUNTIF(Registo!$B$2:$B$501,A149)) -> 0 | T149: =IF(OR(A149="",S149=0),"",LOOKUP(2,1/(Registo!$B$2:$B$501=A149),Registo!$E$2:$E$501))
A150: CAR.06 | B150: Rodapé MDF hidrófugo lacado branco 100 mm | C150: CARP | D150: m | I150: 11 | J150: =IF(AND(A150="",B150=""),"",IF(SUM(E150:H150)>0,SUM(E150:H150),I150)) -> 11 | K150: =IF(J150="","",ROUND(IF(SUM(E150:H150)>0,E150*(1+Config!$C$4)+F150*(1+Config!$C$5)+G150*(1+Config!$C$6)+H150*(1+Config!$C$7),I150*(1+Config!$C$8)),2)) -> 11.22 | M150: =IF(J150="","",IF(L150="",Config!$C$3,L150)) -> 0.2 | N150: =IF(K150="","",ROUND(K150*(1+M150),2)) -> 13.46 | O150: Orçamento próprio (custo, antes de margem) | P150: Ribeira – remodelação (L99) | Q150: 2026 | R150: B | S150: =IF(A150="","",COUNTIF(Registo!$B$2:$B$501,A150)) -> 0 | T150: =IF(OR(A150="",S150=0),"",LOOKUP(2,1/(Registo!$B$2:$B$501=A150),Registo!$E$2:$E$501)) | U150: Inclui agravamento por acesso condicionado (transporte manual 100 m + escadaria, 1.º andar s/ elevador)
A151: CAR.07 | B151: Recuperação de porta interior existente (lixagem, reparação, ferragens, acabamento) | C151: CARP | D151: un | I151: 210 | J151: =IF(AND(A151="",B151=""),"",IF(SUM(E151:H151)>0,SUM(E151:H151),I151)) -> 210 | K151: =IF(J151="","",ROUND(IF(SUM(E151:H151)>0,E151*(1+Config!$C$4)+F151*(1+Config!$C$5)+G151*(1+Config!$C$6)+H151*(1+Config!$C$7),I151*(1+Config!$C$8)),2)) -> 214.2 | M151: =IF(J151="","",IF(L151="",Config!$C$3,L151)) -> 0.2 | N151: =IF(K151="","",ROUND(K151*(1+M151),2)) -> 257.04 | O151: Orçamento próprio (custo, antes de margem) | P151: Ribeira – remodelação (L99) | Q151: 2026 | R151: B | S151: =IF(A151="","",COUNTIF(Registo!$B$2:$B$501,A151)) -> 0 | T151: =IF(OR(A151="",S151=0),"",LOOKUP(2,1/(Registo!$B$2:$B$501=A151),Registo!$E$2:$E$501)) | U151: Inclui agravamento por acesso condicionado (transporte manual 100 m + escadaria, 1.º andar s/ elevador)
J152: =IF(AND(A152="",B152=""),"",IF(SUM(E152:H152)>0,SUM(E152:H152),I152)) | K152: =IF(J152="","",ROUND(IF(SUM(E152:H152)>0,E152*(1+Config!$C$4)+F152*(1+Config!$C$5)+G152*(1+Config!$C$6)+H152*(1+Config!$C$7),I152*(1+Config!$C$8)),2)) | M152: =IF(J152="","",IF(L152="",Config!$C$3,L152)) | N152: =IF(K152="","",ROUND(K152*(1+M152),2)) | S152: =IF(A152="","",COUNTIF(Registo!$B$2:$B$501,A152)) | T152: =IF(OR(A152="",S152=0),"",LOOKUP(2,1/(Registo!$B$2:$B$501=A152),Registo!$E$2:$E$501))
J153: =IF(AND(A153="",B153=""),"",IF(SUM(E153:H153)>0,SUM(E153:H153),I153)) | K153: =IF(J153="","",ROUND(IF(SUM(E153:H153)>0,E153*(1+Config!$C$4)+F153*(1+Config!$C$5)+G153*(1+Config!$C$6)+H153*(1+Config!$C$7),I153*(1+Config!$C$8)),2)) | M153: =IF(J153="","",IF(L153="",Config!$C$3,L153)) | N153: =IF(K153="","",ROUND(K153*(1+M153),2)) | S153: =IF(A153="","",COUNTIF(Registo!$B$2:$B$501,A153)) | T153: =IF(OR(A153="",S153=0),"",LOOKUP(2,1/(Registo!$B$2:$B$501=A153),Registo!$E$2:$E$501))
...

Sheet Config
B1: PARÂMETROS
B3: Margem padrão (sobre o custo) | C3: 0.2 | D3: Igual à folha _Produção_Folha_de_orçamento.xlsx (célula I6)
B4: Encargos – Mão de obra | C4: 0.01 | D4: Folha de orçamento, célula J6
B5: Encargos – Materiais | C5: 0.03 | D5: Folha de orçamento, célula K6
B6: Encargos – Equipamento | C6: 0.02 | D6: Folha de orçamento, célula L6
B7: Encargos – Subempreitada | C7: 0.02 | D7: Folha de orçamento, célula M6
B8: Encargo médio – preço global | C8: 0.02 | D8: Pressuposto: média aplicada a artigos ainda não decompostos – ajustar
B9: IVA – taxa normal | C9: 0.23 | D9: Referência
B10: IVA – taxa reduzida (ARU / reabilitação) | C10: 0.06 | D10: Referência – confirmar enquadramento em cada obra
B13: ESPECIALIDADES
B14: GER | C14: Gerais / Estaleiro
B15: ARQ | C15: Arquitetura
B16: EST | C16: Estruturas
B17: HID | C17: Águas (abastecimento)
B18: PLU | C18: Águas pluviais
B19: ESG | C19: Esgotos
B20: ELE | C20: Eletricidade
B21: ITED | C21: ITED
B22: AVAC | C22: AVAC / Ventilação
B23: GAS | C23: Gás
B24: SCIE | C24: SCIE
B25: TERM | C25: Térmica
... B27: CARP | C27: Carpintarias / Mobiliário

Sheet Registo
A1: Data | B1: Cód. | C1: Obra | D1: Fonte (fornecedor / subempreiteiro / documento) | E1: Preço unitário (€) | F1: Fiabilidade | G1: Observações
